[

	{
		"name": "Car from the Past",
		"author": "Jahir Fiquitiva",
		"url": "https://drive.google.com/uc?export=download&id=1B4Ecf4dYIPtZMM0Srlv1G8tPGCE8uDWG",
		"thumbnail": "https://drive.google.com/uc?export=download&id=1d3IlHtexZGncTQa6N9muZ_OAFXdwAkWr",
		"downloadable": true,
		"size": 5310000,
		"dimensions": "3200 x 4200 px",
		"copyright": "Creative Commons — CC0"
	},	

	{
		"name": "Moon Crates",
		"author": "Jahir Fiquitiva",
		"url": "https://drive.google.com/uc?export=download&id=13g6aPawTDrYH39HJovkrW4ohuZu-yY3k",
		"thumbnail": "https://drive.google.com/uc?export=download&id=1K6zN0N53kMI2tFckzBtQAE7_uxWnrslS",
		"downloadable": true,
		"size": 1930000,
		"dimensions": "3200 x 4200 px",
		"copyright": "Creative Commons — CC0"
	},	
	

	{
		"name": "Sketched Sky",
		"author": "Jahir Fiquitiva",
		"url": "https://drive.google.com/uc?export=download&id=1sN3VAQcBLbTwHbS_I98zDcbRnCrAIsIa",
		"thumbnail": "https://drive.google.com/uc?export=download&id=1HJFzskgprM7Ydi63l38ARE-r4EVa5UUF",
		"downloadable": true,
		"size": 7560000,
		"dimensions": "3200 x 4200 px",
		"copyright": "Creative Commons — CC0"
	}
	
]
