[

	
			{
		"name": "Erratic",
		"author": "tarline and freepik",
		"url": "https://drive.google.com/uc?export=download&id=1AsWbnbm38wIsyUEN6PF1NZAuQnvlFwoZ",
		"thumbnail": "https://drive.google.com/uc?export=download&id=1UKbX-F6iMqxqP2jdr3cw2AXXphAaoLVw",
		"collections": "Abstract",
		"downloadable": true,
		"size": 259000,
		"dimensions": "3200 x 4200 px",
		"copyright": "CreativeCommons - CC0"
	},
		


	
	
	
	
	
	
		{
		"name": "You are the Ocean",
		"author": "Matt Hardy",
		"url": "https://drive.google.com/uc?export=download&id=1YM-Cjwt365Ulbjmbtlnf7HC4Ae2RNYKw",
		"thumbnail": "https://drive.google.com/uc?export=download&id=1hCt5yeaZ8flf885pJogMvDlY78ubMH_q",
		"collections": "Motivational",
		"downloadable": true,
		"size": 2540000,
		"dimensions": "3200 x 4200 px",
		"copyright": "CreativeCommons - CC0"
	},
		



	
			{
		"name": "Fly High",
		"author": "Simplework Designs and Andrea Reiman",
		"url": "https://drive.google.com/uc?export=download&id=158bF2WixeqfWHtuVfFSosoN_e_OSbX8M",
		"thumbnail": "https://drive.google.com/uc?export=download&id=1AG_FRsBREhz_aMuXWkcCUgwhWCm4r9JL",
		"collections": "AMOLED",
		"downloadable": true,
		"size": 253000,
		"dimensions": "3200 x 4200 px",
		"copyright": "CreativeCommons - CC0"
	},
		
	
		
		{
		"name": "SuperMan",
		"author": "Simplework Designs",
		"url": "https://drive.google.com/uc?export=download&id=1rtku13QxgHbsSrIPGJLXaR7i50JW_ZHa",
		"thumbnail": "https://drive.google.com/uc?export=download&id=1WFhRnVia0SHb6-cZvbi_J_b-XbRdLuvp",
		"collections": "Superhero",
		"downloadable": true,
		"size": 137000,
		"dimensions": "3200 x 4200 px",
		"copyright": "CreativeCommons - CC0"
	},
		
	

	
	
	
	
	{
		"name": "Growth",
		"author": "planolla",
		"url": "https://drive.google.com/uc?export=download&id=1CHxiiVOjnXwzkwjtp1tBlmT2sBBW7D9G",
		"thumbnail": "https://drive.google.com/uc?export=download&id=1hh43iAIfNvWQ2UDESh-A3BipcD7bei9Z",
		"collections": "Abstract",
		"downloadable": true,
		"size": 1116000,
		"dimensions": "3200 x 4200 px",
		"copyright": "CreativeCommons - CC0"
	},
	

	
	
	
			{
		"name": "Words Wallpaper",
		"author": "Simplework Designs",
		"url": "https://drive.google.com/uc?export=download&id=11Mc2iPoY-tw2JPD2CPW39UJTjdANXOz2",
		"thumbnail": "https://drive.google.com/uc?export=download&id=1M4qXKv4tsRfiyo3qL_Nu8Ao0icD85aLv",
		"collections": "AMOLED",
		"downloadable": true,
		"size": 2050000,
		"dimensions": "3200 x 4200 px",
		"copyright": "CreativeCommons - CC0"
	},
		
	
		
	
		
	
		{
		"name": "Out of Fucs",
		"author": "Simplework",
		"url": "https://drive.google.com/uc?export=download&id=1NPA_2PnMwqSrVL3NUq3x-7wZ6lHn5aHY",
		"thumbnail": "https://drive.google.com/uc?export=download&id=11_0MKKNER6sywxl8Ux4k2xk08VI5V9ry",
		"collections": "Rude",
		"downloadable": true,
		"size": 126000,
		"dimensions": "3200 x 4200 px",
		"copyright": "CreativeCommons - CC0"
	},
		
	
	
	
	
			{
		"name": "Iron Man",
		"author": "StickPNG",
		"url": "https://drive.google.com/uc?export=download&id=1okbVDLQN2bruFeN4iSTeqvWlkaf1b5MT",
		"thumbnail": "https://drive.google.com/uc?export=download&id=1V3nT8KkaQI-k6oHR-IsNuerkvb9WEaBS",
		"collections": "Superhero",
		"downloadable": true,
		"size": 815000,
		"dimensions": "3200 x 4200 px",
		"copyright": "CreativeCommons - CC0"
	},
		
	
	
	
	
	
	
	
	{
		"name": "Chaos",
		"author": "Thomas Chan and freepik",
		"url": "https://drive.google.com/uc?export=download&id=1VwktBYdut8w2wSN6YIzB2xBZhgGjCOED",
		"thumbnail": "https://drive.google.com/uc?export=download&id=1rpgLath-bJnNKma42efODU6U_OdLrR5q",
		"collections": "Abstract|Photo",
		"downloadable": true,
		"size": 2130000,
		"dimensions": "3200 x 4200 px",
		"copyright": "CreativeCommons - CC0"
	},
	

	
	
	
		
	{
		"name": "Number of the Universe",
		"author": "SimpleWork Designs and freepik",
		"url": "https://drive.google.com/uc?export=download&id=1k20mJwjAFMj0TpszCpGnfsmOMq2_f9wY",
		"thumbnail": "https://drive.google.com/uc?export=download&id=1kZ2oc1CsM3jvJu6pMtSDVLIngF24uPbf",
		"collections": "Abstract",
		"downloadable": true,
		"size": 659000,
		"dimensions": "3200 x 4200 px",
		"copyright": "CreativeCommons - CC0"
	},
	
	
	
	
	
			{
		"name": "Captain America",
		"author": "Flaticon",
		"url": "https://drive.google.com/uc?export=download&id=1ZhvrAYvn_qVN6vqVhOgdEntSY0DRBUXr",
		"thumbnail": "https://drive.google.com/uc?export=download&id=19hTr5lHxHuedvY6C_4DkVixfhevkvLdy",
		"collections": "Superhero",
		"downloadable": true,
		"size": 317000,
		"dimensions": "3200 x 4200 px",
		"copyright": "CreativeCommons - CC0"
	},
		
	
	
	
	

	
	
		{
		"name": "Visionary",
		"author": "SimpleWork Designs and Freepik",
		"url": "https://drive.google.com/uc?export=download&id=1p7dcwPXS9CbGzScAWAQ69rXjaMCO9nQu",
		"thumbnail": "https://drive.google.com/uc?export=download&id=18_fA14rIh3J1plriNYXo_GK_5Jsix88t",
		"collections": "Motivational",
		"downloadable": true,
		"size": 252000,
		"dimensions": "3200 x 4200 px",
		"copyright": "CreativeCommons - CC0"
	},
	
	
	
	
		{
		"name": "Wonder Woman",
		"author": "Simplework Designs",
		"url": "https://drive.google.com/uc?export=download&id=1lARWH6cxl60-3X8E6MXG2RwdH9_ALVIM",
		"thumbnail": "https://drive.google.com/uc?export=download&id=1byW-iVV1QZZeQQogyFANtLA7ZL3OgUaG",
		"collections": "Superhero",
		"downloadable": true,
		"size": 77000,
		"dimensions": "3200 x 4200 px",
		"copyright": "CreativeCommons - CC0"
	},
		
	
	
	
	
	
		{
		"name": "Breathe it Out",
		"author": "SimpleWork Designs",
		"url": "https://drive.google.com/uc?export=download&id=130hYNCfE4gPUFZRfV_NRS8nO9aBOh8il",
		"thumbnail": "https://drive.google.com/uc?export=download&id=1w6hjjCMZI00bH3NJWg-lTPjKiOFyhtL0",
		"collections": "Abstract|Quotes",
		"downloadable": true,
		"size": 676000,
		"dimensions": "3200 x 4200 px",
		"copyright": "CreativeCommons - CC0"
	},
	
	
	
	
	
	
			{
		"name": "Waves",
		"author": "BiZkettE1",
		"url": "https://drive.google.com/uc?export=download&id=1KrwX3Cu8Jp88nvdxevhWh36r4qIZ4lzQ",
		"thumbnail": "https://drive.google.com/uc?export=download&id=1tzBLUxAuWiXIQtw1G7U-wbW-d57zoYlW",
		"collections": "Quotes",
		"downloadable": true,
		"size": 570000,
		"dimensions": "3200 x 4200 px",
		"copyright": "CreativeCommons - CC0"
	},
	
	
	
	
	
	
		{
		"name": "The Incredible Bulk",
		"author": "SimpleWork Designs and Freepik",
		"url": "https://drive.google.com/uc?export=download&id=1iaf1krgXDhn11CjZs8tDvAVX7DpP2WhU",
		"thumbnail": "https://drive.google.com/uc?export=download&id=1BSNwxD9KxiNk0zyMLxAT7J8pL9j9mvp6",
		"collections": "Funny",
		"downloadable": true,
		"size": 436000,
		"dimensions": "3200 x 4200 px",
		"copyright": "CreativeCommons - CC0"
	},
	
	
	
	
		
			{
		"name": "Earphone",
		"author": "photoroyalty and freepik",
		"url": "https://drive.google.com/uc?export=download&id=16QfZgmQCdbyO2n10Ai5bulchhzCqPe9F",
		"thumbnail": "https://drive.google.com/uc?export=download&id=1P2uRLobWt5G1Pm5yS-xyax7nH6DtUevV",
		"collections": "AMOLED",
		"downloadable": true,
		"size": 71000,
		"dimensions": "3200 x 4200 px",
		"copyright": "CreativeCommons - CC0"
	},
		
	

				{
		"name": "I am Batman",
		"author": "Simplework Designs",
		"url": "https://drive.google.com/uc?export=download&id=1d2-8GaSpRt366G-txv2W66-IL8K-pgew",
		"thumbnail": "https://drive.google.com/uc?export=download&id=1UOUHZqcMoLMjodDFPfZh7tUiCSMZ0--S",
		"collections": "Superhero",
		"downloadable": true,
		"size": 436000,
		"dimensions": "3200 x 4200 px",
		"copyright": "CreativeCommons - CC0"
	},

	
	
	
	
	
						{
		"name": "In Pieces",
		"author": "SimpleWork Designs, Vecteezy and freepik",
		"url": "https://drive.google.com/uc?export=download&id=1R4MOlFnMJbhjyiv34iiugKHagXAy_MZN",
		"thumbnail": "https://drive.google.com/uc?export=download&id=1fNDgrSwC1a2X3yZ3RY7QOEyVfn1-lZ4V",
		"collections": "Short Ones|Abstract",
		"downloadable": true,
		"size": 432000,
		"dimensions": "3200 x 4200 px",
		"copyright": "CreativeCommons - CC0"
	},
	

					{
		"name": "Basic",
		"author": "SimpleWork Designs",
		"url": "https://drive.google.com/uc?export=download&id=1-iBYip3VlNnt1y9YD2pGHFyS-0s2jeun",
		"thumbnail": "https://drive.google.com/uc?export=download&id=1XRlhoAKnyLCfz4ttPIe4QQFERBXjUIqK",
		"collections": "Short Ones|Abstract",
		"downloadable": true,
		"size": 35000,
		"dimensions": "3200 x 4200 px",
		"copyright": "CreativeCommons - CC0"
	},
	
	
	
		
	{
		"name": "Salvation-Moksh",
		"author": "SimpleWork Designs",
		"url": "https://drive.google.com/uc?export=download&id=1spzwT3rna-jv7m3TsPy3ZPSmXsvPd0gq",
		"thumbnail": "https://drive.google.com/uc?export=download&id=1Ev_58gwhqh_gTjLudUHflDRkNnItcWCC",
		"collections": "Sanskrit Words",
		"downloadable": true,
		"size": 6900000,
		"dimensions": "3200 x 4200 px",
		"copyright": "CreativeCommons - CC0"
	},
	
	
	
					{
		"name": "Forever Asleep",
		"author": "Simplework Designs",
		"url": "https://drive.google.com/uc?export=download&id=17RsGHFvRj0egUXIInGijytMNWdbow4iO",
		"thumbnail": "https://drive.google.com/uc?export=download&id=1Hz5YckHjmgqsG-loJZclfKY7ZW9JHTnH",
		"collections": "I am Awesome|Funny",
		"downloadable": true,
		"size": 1450000,
		"dimensions": "3200 x 4200 px",
		"copyright": "CreativeCommons - CC0"
	},
	
	
	
	
	
		
			{
		"name": "Android Sun",
		"author": "Simplework Designs",
		"url": "https://drive.google.com/uc?export=download&id=1eDuTIfImSB8Nf81T_V9A6E8eJ2TKcyIs",
		"thumbnail": "https://drive.google.com/uc?export=download&id=16kYZz1v8XGhfXMpjlYxmk-SOp0ge32k1",
		"collections": "AMOLED",
		"downloadable": true,
		"size": 189000,
		"dimensions": "3200 x 4200 px",
		"copyright": "CreativeCommons - CC0"
	},
		
	
	
	
	{
		"name": "Halved Inside",
		"author": "SimpleWork Designs",
		"url": "https://drive.google.com/uc?export=download&id=1Xo_SRSsxFGAQqTV0csRFq3Qi7NI-fR5n",
		"thumbnail": "https://drive.google.com/uc?export=download&id=1NQUQupAJPz4c_JLRF9Aw9dyi-Jr3m3p_",
		"collections": "Short Ones|Abstract",
		"downloadable": true,
		"size": 940000,
		"dimensions": "3200 x 4200 px",
		"copyright": "CreativeCommons - CC0"
	},
	
	
	
	
	
				{
		"name": "Deadpool",
		"author": "Simplework Designs",
		"url": "https://drive.google.com/uc?export=download&id=1ygtbSlHVDjYpADuSJDy3gYPzVjiTjxZQ",
		"thumbnail": "https://drive.google.com/uc?export=download&id=1gJ28sza_JiqUyNlhLdsIYSAt12SGsf4r",
		"collections": "Superhero",
		"downloadable": true,
		"size": 910000,
		"dimensions": "3200 x 4200 px",
		"copyright": "CreativeCommons - CC0"
	},
		
	
	
	
						{
		"name": "Lazy Pug",
		"author": "Simplework Designs",
		"url": "https://drive.google.com/uc?export=download&id=1g0n8R02FzoL6bv3NEdn59oe0mjg1s9lv",
		"thumbnail": "https://drive.google.com/uc?export=download&id=1TYWi7dMfw54_Fcn1UU0nrvxoL0lsYsxl",
		"collections": "I am Awesome|Funny",
		"downloadable": true,
		"size": 108000,
		"dimensions": "3200 x 4200 px",
		"copyright": "CreativeCommons - CC0"
	},
	


	
	{
		"name": "Retro",
		"author": "SimpleWork Designs",
		"url": "https://drive.google.com/uc?export=download&id=1LjVFYd3FXFGou3eulz8U00a1qxYPt2k4",
		"thumbnail": "https://drive.google.com/uc?export=download&id=1PxzxH2YXfz0zOa-EmlPKh3hIIuRQD5RP",
		"collections": "Short Ones|Abstract",
		"downloadable": true,
		"size": 268000,
		"dimensions": "3200 x 4200 px",
		"copyright": "CreativeCommons - CC0"
	},
	
	
	
		
		{
		"name": "Always Supine",
		"author": "SimpleWork Designs",
		"url": "https://drive.google.com/uc?export=download&id=1_HT0IfgrRqnpk602-_uzVTZ4ZUccUNY6",
		"thumbnail": "https://drive.google.com/uc?export=download&id=1uJ-5XOlN7T7pqSY1HunupPAhGUUjmJV7",
		"collections": "I am Awesome",
		"downloadable": true,
		"size": 6110000,
		"dimensions": "3200 x 4200 px",
		"copyright": "CreativeCommons - CC0"
	},
	
	
	

			{
		"name": "Lunar",
		"author": "Luke Stackpoole",
		"url": "https://drive.google.com/uc?export=download&id=1J5_p6tUFezGufHKaqYyit6wM0NeSaGZL",
		"thumbnail": "https://drive.google.com/uc?export=download&id=1iXkTRc_pg4B3zy5z1zDpq-dnqlDkF0tF",
		"collections": "AMOLED",
		"downloadable": true,
		"size": 66000,
		"dimensions": "3200 x 4200 px",
		"copyright": "CreativeCommons - CC0"
	},
		
	

	
	
	
			{
		"name": "Me and Brad Pitt",
		"author": "SimpleWork Designs",
		"url": "https://drive.google.com/uc?export=download&id=10c_Ie3O2KUCNYc7avjO4vZyipWBYIKzL",
		"thumbnail": "https://drive.google.com/uc?export=download&id=1JpLdHxCokcep3sgcx8o63t2EJvtzEbPc",
		"collections": "I am Awesome|Funny",
		"downloadable": true,
		"size": 3530000,
		"dimensions": "3200 x 4200 px",
		"copyright": "CreativeCommons - CC0"
	},
	
	
	
	
	{
		"name": "Broken",
		"author": "SimpleWork Designs",
		"url": "https://drive.google.com/uc?export=download&id=1_bbRAB8zwAgb821CZweqDVi6_F00gDdu",
		"thumbnail": "https://drive.google.com/uc?export=download&id=1JXQbSTPQsZVPgEqfhgXR_ksBQ6T9xsRa",
		"collections": "Short Ones",
		"downloadable": true,
		"size": 2080000,
		"dimensions": "3200 x 4200 px",
		"copyright": "CreativeCommons - CC0"
	},
	
	
	

	
						{
		"name": "Mr Potter",
		"author": "Simplework Designs",
		"url": "https://drive.google.com/uc?export=download&id=1TfW-x08ejP6hzKUVEjW2W4ZMppiKVL3y",
		"thumbnail": "https://drive.google.com/uc?export=download&id=1RfEklbzC5TId2m63sAezdQYZKuRO3kgf",
		"collections": "Movies",
		"downloadable": true,
		"size": 143000,
		"dimensions": "3200 x 4200 px",
		"copyright": "CreativeCommons - CC0"
	},
	
	
	
	
	
	
			{
		"name": "Love my Android",
		"author": "rawpixel.com and freepik",
		"url": "https://drive.google.com/uc?export=download&id=1_hiFUPMzep3XxzxRqWuN5EZ_NgaK3I5b",
		"thumbnail": "https://drive.google.com/uc?export=download&id=164MFx9xt08lbrhzj76NB742vhlmk1_cT",
		"collections": "AMOLED",
		"downloadable": true,
		"size": 23000,
		"dimensions": "3200 x 4200 px",
		"copyright": "CreativeCommons - CC0"
	},
		
	
	
	
	
	
	
					{
		"name": "Consistency is an Issue",
		"author": "Simplework Designs",
		"url": "https://drive.google.com/uc?export=download&id=1dp4lah1kzSa6f_Q8H4BvmMezia_Vs15I",
		"thumbnail": "https://drive.google.com/uc?export=download&id=1csmKkrfrHVvyBc3pCIjP1bk2bbxbe_qK",
		"collections": "Funny",
		"downloadable": true,
		"size": 48000,
		"dimensions": "3200 x 4200 px",
		"copyright": "CreativeCommons - CC0"
	},
	

	
	

			{
		"name": "Alone",
		"author": "Adam Miller",
		"url": "https://drive.google.com/uc?export=download&id=1Aw3pa13tmruWTTPQvNjbVnHlU1H6dHS_",
		"thumbnail": "https://drive.google.com/uc?export=download&id=1fRQkNFR9QtXdFCPk9bdzHz8xRYHRjkMA",
		"collections": "AMOLED",
		"downloadable": true,
		"size": 1080000,
		"dimensions": "3200 x 4200 px",
		"copyright": "CreativeCommons - CC0"
	},
		
	
	
	
	{
		"name": "Omega",
		"author": "SimpleWork Designs",
		"url": "https://drive.google.com/uc?export=download&id=1fwdF7hhUHfggFneQ6lw8LxaXveadjnEh",
		"thumbnail": "https://drive.google.com/uc?export=download&id=1tt_BdUMaurL5DV-tZJOR7W6q1DSwca11",
		"collections": "Short Ones|Abstract",
		"downloadable": true,
		"size": 249000,
		"dimensions": "3200 x 4200 px",
		"copyright": "CreativeCommons - CC0"
	},
	
	
	

	{
		"name": "One of a Kind",
		"author": "SimpleWork Designs",
		"url": "https://drive.google.com/uc?export=download&id=1Wu1QJXYhkRoiQ6JjXMXFy6T4v7mUSRRg",
		"thumbnail": "https://drive.google.com/uc?export=download&id=1ZnUuitwh-Ch0JcbER22J-V2SqahiRkM9",
		"collections": "I am Awesome",
		"downloadable": true,
		"size": 8820000,
		"dimensions": "3200 x 4200 px",
		"copyright": "CreativeCommons - CC0"
	},
	
	
	
	
	
			{
		"name": "Blood Sweat and Tears",
		"author": "freepik",
		"url": "https://drive.google.com/uc?export=download&id=1Y_dSeoG_A7QDW2xivQxxgPW9chktlNdx",
		"thumbnail": "https://drive.google.com/uc?export=download&id=1tsp_nVdMCKVZHjDaE1CxU7AmXW2Rk0s2",
		"collections": "AMOLED",
		"downloadable": true,
		"size": 102000,
		"dimensions": "3200 x 4200 px",
		"copyright": "CreativeCommons - CC0"
	},
		
	
	
	
	{
		"name": "Indifferent",
		"author": "SimpleWork Designs",
		"url": "https://drive.google.com/uc?export=download&id=1OwGUWvlZf-DnVGleeS4F3zIHvEyh0mOt",
		"thumbnail": "https://drive.google.com/uc?export=download&id=1mH0f57EtKLiNXvVUDAubqXEJJN7nWCUK",
		"collections": "Short Ones|Abstract",
		"downloadable": true,
		"size": 72000,
		"dimensions": "3200 x 4200 px",
		"copyright": "CreativeCommons - CC0"
	},
	
	
			

	
				{
		"name": "Left Behind",
		"author": "Oskars Sylwan",
		"url": "https://drive.google.com/uc?export=download&id=1kbkqsAnAhtbAE7tLkfiGjLUKbhLVilXd",
		"thumbnail": "https://drive.google.com/uc?export=download&id=1CUgA-A8cnAciHW8uOA4fWgifeshmVQuP",
		"collections": "AMOLED",
		"downloadable": true,
		"size": 93000,
		"dimensions": "3200 x 4200 px",
		"copyright": "CreativeCommons - CC0"
	},
		
	
	
	
							{
		"name": "I am Historic",
		"author": "SimpleWork Designs and freepik",
		"url": "https://drive.google.com/uc?export=download&id=1ruFZ5WxQt3heHlEtRhPV3UsTNO-mrNGX",
		"thumbnail": "https://drive.google.com/uc?export=download&id=16GxUPXVqUusy7HhSjZ52mU3n8KAOgXfz",
		"collections": "Short Ones|I am Awesome",
		"downloadable": true,
		"size": 729000,
		"dimensions": "3200 x 4200 px",
		"copyright": "CreativeCommons - CC0"
	},
	
	
		
	{
		"name": "Unseen",
		"author": "SimpleWork Designs",
		"url": "https://drive.google.com/uc?export=download&id=1jPVnIez1HK-lx0qMXljVw9tOqlYnJCds",
		"thumbnail": "https://drive.google.com/uc?export=download&id=1vnX9TddDYWKO06H2LRZiu8a9_IIJb2yk",
		"collections": "Short Ones|Abstract",
		"downloadable": true,
		"size": 558000,
		"dimensions": "3200 x 4200 px",
		"copyright": "CreativeCommons - CC0"
	},
	
	
	
	
	
	
	
	

	
				{
		"name": "Eclipse",
		"author": "SimpleWork Designs and freepik",
		"url": "https://drive.google.com/uc?export=download&id=1LGjK2jnPZ7CVqKkrs07VbsNKKn055vCg",
		"thumbnail": "https://drive.google.com/uc?export=download&id=1fnlcU36a6L_gSiKWBo1gx5GpK6r796TE",
		"collections": "Abstract|Quotes",
		"downloadable": true,
		"size": 228000,
		"dimensions": "3200 x 4200 px",
		"copyright": "CreativeCommons - CC0"
	},
	


		

		


	
			{
		"name": "Perfect Aim",
		"author": "SimpleWork Designs",
		"url": "https://drive.google.com/uc?export=download&id=1bIX43r2LpCy7mNPvtHkl8jNK0EJlBYNK",
		"thumbnail": "https://drive.google.com/uc?export=download&id=1pnodIiqF0ybbWhbSmaFm7WmSgIwQwwdq",
		"collections": "Motivational",
		"downloadable": true,
		"size": 290000,
		"dimensions": "3200 x 4200 px",
		"copyright": "CreativeCommons - CC0"
	},
	

					{
		"name": "I got Amoled",
		"author": "Simplework Design",
		"url": "https://drive.google.com/uc?export=download&id=1wNPpyXJdCpvzDUNDObxnnj0Gb53qyeLy",
		"thumbnail": "https://drive.google.com/uc?export=download&id=12Gimi9wlw65TT8ICuxQC7KXbXLcBNWQ3",
		"collections": "AMOLED",
		"downloadable": true,
		"size": 89000,
		"dimensions": "3200 x 4200 px",
		"copyright": "CreativeCommons - CC0"
	},
		
	
	
	
		{
		"name": "Stupid PPL",
		"author": "macrovector from freepik and SimpleWork Designs",
		"url": "https://drive.google.com/uc?export=download&id=1ayo6SunmbjTlys9nDRbJynhMRjD8Pcjb",
		"thumbnail": "https://drive.google.com/uc?export=download&id=1cvYyoMHnW2eBx3glYDx_MzbWUDWYzUoo",
		"collections": "Funny|Rude",
		"downloadable": true,
		"size": 8260000,
		"dimensions": "3200 x 4200 px",
		"copyright": "CreativeCommons - CC0"
	},
	
	
		
		
	{
		"name": "Middle Finger",
		"author": "SimpleWork Designs",
		"url": "https://drive.google.com/uc?export=download&id=1QyZTuBBiNsaVm_x_-YjbJjP7IYlMO0MP",
		"thumbnail": "https://drive.google.com/uc?export=download&id=1fdSeYtg7Cro0AiMq6RQq1xWsnXfbFGPL",
		"collections": "Emojis",
		"downloadable": true,
		"size": 287000,
		"dimensions": "3200 x 4200 px",
		"copyright": "CreativeCommons - CC0"
	},
	
	
	
		
	
		{
		"name": "Classy as Fuc",
		"author": "SimpleWork Designs",
		"url": "https://drive.google.com/uc?export=download&id=1ZT7YrnHyPE_XeY3Vr59TiwBKklS16UPI",
		"thumbnail": "https://drive.google.com/uc?export=download&id=1Ty2zkEIQrGd0XicXUKYK5v3ftGUW1VGB",
		"collections": "I am Awesome",
		"downloadable": true,
		"size": 4670000,
		"dimensions": "3200 x 4200 px",
		"copyright": "CreativeCommons - CC0"
	},
	
	


	
	{
		"name": "STFU",
		"author": "SimpleWork Designs",
		"url": "https://drive.google.com/uc?export=download&id=1fgdZop9eHHb593VCcYNQGVUgg6Z9NBSy",
		"thumbnail": "https://drive.google.com/uc?export=download&id=1jz2AySXDEP7yW6JWrhR_VAF72B3t7T7a",
		"collections": "Funny|Rude",
		"downloadable": true,
		"size": 195000,
		"dimensions": "3200 x 4200 px",
		"copyright": "CreativeCommons - CC0"
	},
			
	
	
	
	
			{
		"name": "Infinte Things",
		"author": "SimpleWork Designs and kreativekolors",
		"url": "https://drive.google.com/uc?export=download&id=14Jc3komVH0RZvosuKfIhN0JgcvjHFVdO",
		"thumbnail": "https://drive.google.com/uc?export=download&id=1V-H04LIytsZeKq6P188RQBRau2-9Mtd9",
		"collections": "Funny",
		"downloadable": true,
		"size": 89000,
		"dimensions": "3200 x 4200 px",
		"copyright": "CreativeCommons - CC0"
	},
	

	

	

	
	
	
			{
		"name": "Titanic",
		"author": "SimpleWork Designs",
		"url": "https://drive.google.com/uc?export=download&id=1JKo_-aOMjMQIiCCL3RUIsfRrAZWuRe0u",
		"thumbnail": "https://drive.google.com/uc?export=download&id=1vC_jmMB8aOQAmclPTXzMlF5RH43GVqWd",
		"collections": "Movies",
		"downloadable": true,
		"size": 945000,
		"dimensions": "3200 x 4200 px",
		"copyright": "CreativeCommons - CC0"
	},
	

		
			{
		"name": "Born This Way",
		"author": "Simplework Designs",
		"url": "https://drive.google.com/uc?export=download&id=1sO0yDQYOSltHqXVrXmefE-ds0r9lx0JW",
		"thumbnail": "https://drive.google.com/uc?export=download&id=1ib628jwfyKvC5CtFKtdjHC4un1RfclCw",
		"collections": "Lyrics",
		"downloadable": true,
		"size": 120000,
		"dimensions": "3200 x 4200 px",
		"copyright": "CreativeCommons - CC0"
	},
	



	
				{
		"name": "Teresa",
		"author": "Simplework Designs",
		"url": "https://drive.google.com/uc?export=download&id=1vPXV8RM4vMvtft64HaqL_5jezTKXPDwR",
		"thumbnail": "https://drive.google.com/uc?export=download&id=1S5jyohcrOmVnKT7iRVrrKOowtBogWNYJ",
		"collections": "Quotes",
		"downloadable": true,
		"size": 1530000,
		"dimensions": "3200 x 4200 px",
		"copyright": "CreativeCommons - CC0"
	},
	
	
	
					{
		"name": "On the Edge",
		"author": "Simplework Designs",
		"url": "https://drive.google.com/uc?export=download&id=1bFmQviAZhwgpdT8zh7WKxAq9joXlCoGM",
		"thumbnail": "https://drive.google.com/uc?export=download&id=1voUJtTQq5xcnumEGa2GZclW3cEE5lJ_t",
		"collections": "Abstract|Motivational|Short Ones",
		"downloadable": true,
		"size": 61000,
		"dimensions": "3200 x 4200 px",
		"copyright": "CreativeCommons - CC0"
	},
	
	
					{
		"name": "Bad Example",
		"author": "Simplework Designs",
		"url": "https://drive.google.com/uc?export=download&id=1R5hSqKiHRgyC6lvG1HAx_s4-a0ZDQjqt",
		"thumbnail": "https://drive.google.com/uc?export=download&id=1N4rH6tg2Bt3CaJ2dFaKxLhaO9LP0J73d",
		"collections": "Funny",
		"downloadable": true,
		"size": 160000,
		"dimensions": "3200 x 4200 px",
		"copyright": "CreativeCommons - CC0"
	},
	
	
	
	
			{
		"name": "All Around White",
		"author": "SimpleWork Designs",
		"url": "https://drive.google.com/uc?export=download&id=1f3ryLnQW2Bxr_n6so5e8mkzl3B_EgXlp",
		"thumbnail": "https://drive.google.com/uc?export=download&id=12RPi8oWtU68td8Z2uzbi9fH8KY9VdbDO",
		"collections": "Short Ones|Abstract",
		"downloadable": true,
		"size": 228000,
		"dimensions": "3200 x 4200 px",
		"copyright": "CreativeCommons - CC0"
	},
	
	
					{
		"name": "Nobody Like Me",
		"author": "Simplework Designs",
		"url": "https://drive.google.com/uc?export=download&id=1zPmHKoj8FHBADOEYW-5s1xNErAbdGhZz",
		"thumbnail": "https://drive.google.com/uc?export=download&id=1gPyXyJsJ09rH3Z9YuCnFECK_kzmk0axz",
		"collections": "I am Awesome",
		"downloadable": true,
		"size": 110000,
		"dimensions": "3200 x 4200 px",
		"copyright": "CreativeCommons - CC0"
	},
	
	
					{
		"name": "Damnson",
		"author": "Simplework Designs",
		"url": "https://drive.google.com/uc?export=download&id=1giFXhEyjqBc5sjMv7EOk16W611LKarg2",
		"thumbnail": "https://drive.google.com/uc?export=download&id=1Y_NKuEQ61ATWC3W7cyzpzowuHL-Gyr96",
		"collections": "Brand",
		"downloadable": true,
		"size": 135000,
		"dimensions": "3200 x 4200 px",
		"copyright": "CreativeCommons - CC0"
	},
	
	
					{
		"name": "My Dark Side",
		"author": "Simplework Designs",
		"url": "https://drive.google.com/uc?export=download&id=1SRFI_aDPWtYHFbOQ2dthutMl6fJinWat",
		"thumbnail": "https://drive.google.com/uc?export=download&id=1McJPVP8JaksQ7qkuIq18pOFu9H6rOPyd",
		"collections": "Rude",
		"downloadable": true,
		"size": 207000,
		"dimensions": "3200 x 4200 px",
		"copyright": "CreativeCommons - CC0"
	},
	
	
					{
		"name": "Infinte Things",
		"author": "Simplework Designs",
		"url": "https://drive.google.com/uc?export=download&id=14Jc3komVH0RZvosuKfIhN0JgcvjHFVdO",
		"thumbnail": "https://drive.google.com/uc?export=download&id=1V-H04LIytsZeKq6P188RQBRau2-9Mtd9",
		"collections": "Funny",
		"downloadable": true,
		"size": 86000,
		"dimensions": "3200 x 4200 px",
		"copyright": "CreativeCommons - CC0"
	},
	
	
					{
		"name": "The Godfather",
		"author": "Simplework Designs",
		"url": "https://drive.google.com/uc?export=download&id=1SZyl_x--cJqI4d4-B_6MAyBs95HOYt7M",
		"thumbnail": "https://drive.google.com/uc?export=download&id=1xzhTX4Y3zPXvDvqRHMaKWPWNBkxpIvEy",
		"collections": "Movies",
		"downloadable": true,
		"size": 377000,
		"dimensions": "3200 x 4200 px",
		"copyright": "CreativeCommons - CC0"
	},
	
	
					{
		"name": "Verbal Eyes",
		"author": "Simplework Designs",
		"url": "https://drive.google.com/uc?export=download&id=1W8l7YzANnKdFduAuwiWUabwxG2gEQfO0",
		"thumbnail": "https://drive.google.com/uc?export=download&id=1LsFqeXI_JKc00OYBjoBPKucE5dSEoIoN",
		"collections": "Romantic",
		"downloadable": true,
		"size": 253000,
		"dimensions": "3200 x 4200 px",
		"copyright": "CreativeCommons - CC0"
	},
	
	
					{
		"name": "Euphoric",
		"author": "Simplework Designs",
		"url": "https://drive.google.com/uc?export=download&id=1kxmNB2nMC6PnwPsPP0joF-HvM-j9Fb1M",
		"thumbnail": "https://drive.google.com/uc?export=download&id=1BtW-HPGzLB5Dkd6NHgzsDxvRXUs4vils",
		"collections": "Short Ones",
		"downloadable": true,
		"size": 19000,
		"dimensions": "3200 x 4200 px",
		"copyright": "CreativeCommons - CC0"
	},
	
	
					{
		"name": "Spell Bee Champs",
		"author": "Simplework Designs",
		"url": "https://drive.google.com/uc?export=download&id=1f2JmkNWnqw23bQpmg4ZUxgCKDyzD23ab",
		"thumbnail": "https://drive.google.com/uc?export=download&id=1rC5llnI9-15PT1wZndYJmPGGc6xRwugS",
		"collections": "Brand",
		"downloadable": true,
		"size": 153000,
		"dimensions": "3200 x 4200 px",
		"copyright": "CreativeCommons - CC0"
	},
	
	
					{
		"name": "Patient Musk",
		"author": "Simplework Designs",
		"url": "https://drive.google.com/uc?export=download&id=1ZcyCUwfL26y2bNVJEvPjjRx6mi4MbiNv",
		"thumbnail": "https://drive.google.com/uc?export=download&id=1h0U2kWXfRapKQALIcyECxeuHpklF4e1i",
		"collections": "",
		"downloadable": true,
		"size": 800000,
		"dimensions": "3200 x 4200 px",
		"copyright": "CreativeCommons - CC0"
	},
	
	
					{
		"name": "Overthink",
		"author": "Simplework Designs",
		"url": "https://drive.google.com/uc?export=download&id=1TOa4K5XCzdJ9U_oA5feGFvcmtWMeTfRY",
		"thumbnail": "https://drive.google.com/uc?export=download&id=1iWsEjoOC9rCkLpGPGM-tCXgS4gWQY83T",
		"collections": "Clever|Quotes",
		"downloadable": true,
		"size": 176000,
		"dimensions": "3200 x 4200 px",
		"copyright": "CreativeCommons - CC0"
	},
	
	
					{
		"name": "No Stupid Today",
		"author": "Simplework Designs",
		"url": "https://drive.google.com/uc?export=download&id=1a6h8aQAWQs4S2LWvIRs7Tt-OAdKD2FuJ",
		"thumbnail": "https://drive.google.com/uc?export=download&id=1Csc3v8X_5_93Io4Qfx_pe3L2aXcMnODT",
		"collections": "Rude|Funny",
		"downloadable": true,
		"size": 206000,
		"dimensions": "3200 x 4200 px",
		"copyright": "CreativeCommons - CC0"
	},
	
	

	
					{
		"name": "Drake the Wise",
		"author": "Simplework Designs",
		"url": "https://drive.google.com/uc?export=download&id=114WRVzmPvzL__LipECYGMd18JrSMw1ce",
		"thumbnail": "https://drive.google.com/uc?export=download&id=1-aG4-KvdnY-GWr8D-gAbchQdH2HLgxdG",
		"collections": "Lyrics",
		"downloadable": true,
		"size": 445000,
		"dimensions": "3200 x 4200 px",
		"copyright": "CreativeCommons - CC0"
	},
	
	
					{
		"name": "The Best",
		"author": "Simplework Designs",
		"url": "https://drive.google.com/uc?export=download&id=13maH7ycLId4a4bkHp4lbNOyDCoUqaYpo",
		"thumbnail": "https://drive.google.com/uc?export=download&id=1yn1hLFm58i0qjGZYnacjRHdhZfFJzxhr",
		"collections": "Motivational",
		"downloadable": true,
		"size": 173000,
		"dimensions": "3200 x 4200 px",
		"copyright": "CreativeCommons - CC0"
	},
	
	
					{
		"name": "Beast Inside",
		"author": "Simplework Designs",
		"url": "https://drive.google.com/uc?export=download&id=1zSNJmt_vHlTU8mVZqDrYbfWhpJOpoKVz",
		"thumbnail": "https://drive.google.com/uc?export=download&id=1sBApWH04ikh_BgiQ3sZkR0iajAIPWA4c",
		"collections": "I am Awesome",
		"downloadable": true,
		"size": 106000,
		"dimensions": "3200 x 4200 px",
		"copyright": "CreativeCommons - CC0"
	},
	
	
	
	
	
					{
		"name": "The Genius of Einstein",
		"author": "Simplework Designs",
		"url": "https://drive.google.com/uc?export=download&id=1WzDwFr_HROiMyhtsILU6hWlzoqeGzBeB",
		"thumbnail": "https://drive.google.com/uc?export=download&id=1tIDLSWFC4bm8xnK4Job9NTc42EDvazpL",
		"collections": "Quotes",
		"downloadable": true,
		"size": 865000,
		"dimensions": "3200 x 4200 px",
		"copyright": "CreativeCommons - CC0"
	},
	
	

	
					{
		"name": "La La La La La",
		"author": "Simplework Designs",
		"url": "https://drive.google.com/uc?export=download&id=1ZGfZtHsoW9u0mTYSQSmHP8xUIO1RpJ_G",
		"thumbnail": "https://drive.google.com/uc?export=download&id=1QgsMewJDsz78HCn6EeglT1BtL_WzAwPI",
		"collections": "I am Awesome",
		"downloadable": true,
		"size": 116000,
		"dimensions": "3200 x 4200 px",
		"copyright": "CreativeCommons - CC0"
	},
	
	
					{
		"name": "My Pities",
		"author": "Simplework Designs",
		"url": "https://drive.google.com/uc?export=download&id=1LtFuW0XaSLN7-OusFK-flFJHjsehpofB",
		"thumbnail": "https://drive.google.com/uc?export=download&id=1nSh1r2aPCB3EZ39bI1N6brtWgzJwNCQz",
		"collections": "Rude",
		"downloadable": true,
		"size": 1250000,
		"dimensions": "3200 x 4200 px",
		"copyright": "CreativeCommons - CC0"
	},
	
	
					{
		"name": "Baby you're a Firework",
		"author": "Simplework Designs",
		"url": "https://drive.google.com/uc?export=download&id=10NjYVyRwmHXchKzQf-BJt5PPNOO1dj2G",
		"thumbnail": "https://drive.google.com/uc?export=download&id=1isD_YzQ84SWlS-wB7McabRzLaeVVsSw1",
		"collections": "I am Awesome",
		"downloadable": true,
		"size": 504000,
		"dimensions": "3200 x 4200 px",
		"copyright": "CreativeCommons - CC0"
	},
	

					{
		"name": "Adibas",
		"author": "Simplework Designs",
		"url": "https://drive.google.com/uc?export=download&id=1Pf-dHpQ1G39_JEWcnfT6uj0q07wI3XAZ",
		"thumbnail": "https://drive.google.com/uc?export=download&id=1YKu_Pw_g0wXhQF2De0pfyv2w8lXgFUsd",
		"collections": "Brand|Motivational|Funny",
		"downloadable": true,
		"size": 127000,
		"dimensions": "3200 x 4200 px",
		"copyright": "CreativeCommons - CC0"
	},
	
	
					{
		"name": "Pure",
		"author": "Simplework Designs",
		"url": "https://drive.google.com/uc?export=download&id=14J9I1pR1QYQ81whDKUTo89dFfF3m5o_5",
		"thumbnail": "https://drive.google.com/uc?export=download&id=1cYnDxQHcFogsS44ftZEDjISVma7KzHKc",
		"collections": "Sanskrit Words",
		"downloadable": true,
		"size": 6940000,
		"dimensions": "3200 x 4200 px",
		"copyright": "CreativeCommons - CC0"
	},
	
	
					{
		"name": "Namaste",
		"author": "Simplework Designs",
		"url": "https://drive.google.com/uc?export=download&id=1ub7SuyWNUdQ39Woy8MTKGpFI7Od-DpVf",
		"thumbnail": "https://drive.google.com/uc?export=download&id=1woUYjpCWdoBiOM5N7IaM-uExrxFe8cqs",
		"collections": "Sanskrit Words",
		"downloadable": true,
		"size": 7310000,
		"dimensions": "3200 x 4200 px",
		"copyright": "CreativeCommons - CC0"
	},
	
	
					{
		"name": "Wisdom",
		"author": "Simplework Designs",
		"url": "https://drive.google.com/uc?export=download&id=17YTy7ukuuqPMm8U5IlVFZyLE9izeKP5e",
		"thumbnail": "https://drive.google.com/uc?export=download&id=1JtHeyHF_4AmxLv_01rEim66kkaYxpVMe",
		"collections": "Sanskrit Words",
		"downloadable": true,
		"size": 7508000,
		"dimensions": "3200 x 4200 px",
		"copyright": "CreativeCommons - CC0"
	},
	
	
					{
		"name": "Peace",
		"author": "Simplework Designs",
		"url": "https://drive.google.com/uc?export=download&id=1Cdtz4jWCHDZS6h66VnyEy20sI0nzw3B9",
		"thumbnail": "https://drive.google.com/uc?export=download&id=1N0sXbrbnhqVafLHch6FUR2vP_23WJmSd",
		"collections": "Sanskrit Words",
		"downloadable": true,
		"size": 7445000,
		"dimensions": "3200 x 4200 px",
		"copyright": "CreativeCommons - CC0"
	},
	
	
					{
		"name": "Divine",
		"author": "Simplework Designs",
		"url": "https://drive.google.com/uc?export=download&id=1iY5_FSowOworYzvPIpv1cGYQEBjIGnQv",
		"thumbnail": "https://drive.google.com/uc?export=download&id=11VOiRanOZG_Yg0bU4ZodcukW5bQvrOzv",
		"collections": "Sanskrit Words",
		"downloadable": true,
		"size": 6881000,
		"dimensions": "3200 x 4200 px",
		"copyright": "CreativeCommons - CC0"
	},
	
	
					{
		"name": "Love",
		"author": "Simplework Designs",
		"url": "https://drive.google.com/uc?export=download&id=1ARRvy3SQG2KPbIfUzZwLTypumofofc4A",
		"thumbnail": "https://drive.google.com/uc?export=download&id=1RV3PGWqbThPB7g99ecpvznuiNg85_W9J",
		"collections": "Sanskrit Words",
		"downloadable": true,
		"size": 7317000,
		"dimensions": "3200 x 4200 px",
		"copyright": "CreativeCommons - CC0"
	},
	
	
					{
		"name": "Dedication",
		"author": "Simplework Designs",
		"url": "https://drive.google.com/uc?export=download&id=1bE8xqNZVS9sEX_vYvCDX4xkQeKvr64mf",
		"thumbnail": "https://drive.google.com/uc?export=download&id=1EZKMEo3rU3YZOLbs46jHKAzREPkncCCQ",
		"collections": "Sanskrit Words",
		"downloadable": true,
		"size": 7267000,
		"dimensions": "3200 x 4200 px",
		"copyright": "CreativeCommons - CC0"
	},
	
	
					{
		"name": "The Peak",
		"author": "Simplework Designs",
		"url": "https://drive.google.com/uc?export=download&id=1S6-wnda2A8aD3lea6ER_HDPpSou412_W",
		"thumbnail": "https://drive.google.com/uc?export=download&id=1FtQBo129QBDSjZpE-_HAkZ4jzZuIRORi",
		"collections": "Sanskrit Words",
		"downloadable": true,
		"size": 7277000,
		"dimensions": "3200 x 4200 px",
		"copyright": "CreativeCommons - CC0"
	},
	
	
					{
		"name": "Life Goals",
		"author": "Simplework Designs",
		"url": "https://drive.google.com/uc?export=download&id=18KAaziARzmP2T5mGapeH7YNJcVM_Ueef",
		"thumbnail": "https://drive.google.com/uc?export=download&id=1m9FVDZk4OnUOGiHsOWGnWYQ-gc5gNMLq",
		"collections": "Motivational",
		"downloadable": true,
		"size": 2159000,
		"dimensions": "3200 x 4200 px",
		"copyright": "CreativeCommons - CC0"
	},
	
	
					{
		"name": "LoUnreal",
		"author": "Simplework Designs",
		"url": "https://drive.google.com/uc?export=download&id=1I54pcG-jG8V66A6koLbn9zz3q1fj7yGk",
		"thumbnail": "https://drive.google.com/uc?export=download&id=1qdaIlgVz5vdzmX4knoJ_NJrUnEyDnlFb",
		"collections": "Brand",
		"downloadable": true,
		"size": 2478000,
		"dimensions": "3200 x 4200 px",
		"copyright": "CreativeCommons - CC0"
	},
	
	
					{
		"name": "Choka Cola",
		"author": "Simplework Designs",
		"url": "https://drive.google.com/uc?export=download&id=12At0tXzdpVKPCd51oBGMRTcQy6wgLoB5",
		"thumbnail": "https://drive.google.com/uc?export=download&id=160HH8tEE-l_wLuu_r-mfH64HHAn14r9-",
		"collections": "Brand",
		"downloadable": true,
		"size": 5990000,
		"dimensions": "3200 x 4200 px",
		"copyright": "CreativeCommons - CC0"
	},
	
	
					{
		"name": "Mcwhat",
		"author": "Simplework Designs",
		"url": "https://drive.google.com/uc?export=download&id=1lo-zCoTkTvVxlepZu3GajU_tFpj37u_Z",
		"thumbnail": "https://drive.google.com/uc?export=download&id=1PBcgDckQcKBqBZdLjz_m7yPEXXg44BKX",
		"collections": "Brand",
		"downloadable": true,
		"size": 5842000,
		"dimensions": "3200 x 4200 px",
		"copyright": "CreativeCommons - CC0"
	},
	
	
					{
		"name": "Pika Pika",
		"author": "Simplework Designs",
		"url": "https://drive.google.com/uc?export=download&id=1bqrJMH9hQPyicsZcnv90b9WBiucuhZtg",
		"thumbnail": "https://drive.google.com/uc?export=download&id=1xr1ee_Ctf1dAyZArMlyc1mSZD0t-M4i9",
		"collections": "Emojis",
		"downloadable": true,
		"size": 291000,
		"dimensions": "3200 x 4200 px",
		"copyright": "CreativeCommons - CC0"
	},
	
	
					{
		"name": "Creepy Smile",
		"author": "Simplework Designs",
		"url": "https://drive.google.com/uc?export=download&id=18v5WlROrrhUlra864EnbnLXWUQUiyL9t",
		"thumbnail": "https://drive.google.com/uc?export=download&id=1S0Io985rpwlWYGeahitIHItRTEzJcNKJ",
		"collections": "Emojis",
		"downloadable": true,
		"size": 285000,
		"dimensions": "3200 x 4200 px",
		"copyright": "CreativeCommons - CC0"
	},
	
	
					{
		"name": "Sobs",
		"author": "Simplework Designs",
		"url": "https://drive.google.com/uc?export=download&id=1dLYNpBXa67vp4IiYQRVySMinzhP91oBr",
		"thumbnail": "https://drive.google.com/uc?export=download&id=1MZ3ktsFtYl17Z1hGxQLPlycThPAjts3I",
		"collections": "Emojis",
		"downloadable": true,
		"size": 289000,
		"dimensions": "3200 x 4200 px",
		"copyright": "CreativeCommons - CC0"
	},
	
	
					{
		"name": "Lemme Sleep",
		"author": "Simplework Designs",
		"url": "https://drive.google.com/uc?export=download&id=1Kgua6EOGtTUX9h06km_6qjj3tzKDB_T2",
		"thumbnail": "https://drive.google.com/uc?export=download&id=1LpRzLAcygPi4SEtkUb9Xm4mviOquB_RM",
		"collections": "Emojis",
		"downloadable": true,
		"size": 289000,
		"dimensions": "3200 x 4200 px",
		"copyright": "CreativeCommons - CC0"
	},
	
	
					{
		"name": "Horny AF",
		"author": "Simplework Designs",
		"url": "https://drive.google.com/uc?export=download&id=10zKCWGxNTN6BbQbeLPCh5dqYCUGDM0K2",
		"thumbnail": "https://drive.google.com/uc?export=download&id=1sbgXkl7Cfc9guPYaq2ufZivzPQAJUTgQ",
		"collections": "Emojis",
		"downloadable": true,
		"size": 288000,
		"dimensions": "3200 x 4200 px",
		"copyright": "CreativeCommons - CC0"
	},
	
	
					{
		"name": "Meh!",
		"author": "Simplework Designs",
		"url": "https://drive.google.com/uc?export=download&id=1LOygklXn8amSkJrXpyTVsoZYp6GU5YHx",
		"thumbnail": "https://drive.google.com/uc?export=download&id=1O2TL16crHtunbYRN-hE2pYZMZWsVS4rF",
		"collections": "Emojis",
		"downloadable": true,
		"size": 291000,
		"dimensions": "3200 x 4200 px",
		"copyright": "CreativeCommons - CC0"
	},
	
	
					{
		"name": "Namaskar",
		"author": "Simplework Designs",
		"url": "https://drive.google.com/uc?export=download&id=1wo66GalBqScLCeVVjsi9hy1u0oHPKybS",
		"thumbnail": "https://drive.google.com/uc?export=download&id=1aMRBZfVM0fWgcchqbfN2gBPPMaQ1W1Ia",
		"collections": "Emojis",
		"downloadable": true,
		"size": 286000,
		"dimensions": "3200 x 4200 px",
		"copyright": "CreativeCommons - CC0"
	},
	
	
					{
		"name": "Nocturnal",
		"author": "Simplework Designs",
		"url": "https://drive.google.com/uc?export=download&id=1C_8XYHHw3nnqit4us4Xmb9sff7FZUr91",
		"thumbnail": "https://drive.google.com/uc?export=download&id=1txvD62uw0v3dYYRvbUEx5vQFEm5jJ0sY",
		"collections": "Emojis",
		"downloadable": true,
		"size": 287000,
		"dimensions": "3200 x 4200 px",
		"copyright": "CreativeCommons - CC0"
	},
	
	
					{
		"name": "Teddy",
		"author": "Simplework Designs",
		"url": "https://drive.google.com/uc?export=download&id=1T5orF9sEPbnrKyNfoJcU4BKhuq2PF0Ng",
		"thumbnail": "https://drive.google.com/uc?export=download&id=1gfAnYtKmnthWg7OAwrS45NvRnNiaxMQU",
		"collections": "Emojis",
		"downloadable": true,
		"size": 289000,
		"dimensions": "3200 x 4200 px",
		"copyright": "CreativeCommons - CC0"
	},
	
	
					{
		"name": "Kiss",
		"author": "Simplework Designs",
		"url": "https://drive.google.com/uc?export=download&id=1fpRPslQx90YQZJwXJzXzqzdEyKCtvtSZ",
		"thumbnail": "https://drive.google.com/uc?export=download&id=16sygBy2ygJJLSNhAxbPX3ODP1WohwoVH",
		"collections": "Emojis",
		"downloadable": true,
		"size": 288000,
		"dimensions": "3200 x 4200 px",
		"copyright": "CreativeCommons - CC0"
	},
	
	
					{
		"name": "Cmon",
		"author": "Simplework Designs",
		"url": "https://drive.google.com/uc?export=download&id=1efqmYmhvHwS7H1wWLpxmEZlLv0afvqBF",
		"thumbnail": "https://drive.google.com/uc?export=download&id=1SenvwbgBewR_SegnM47EsB6mIvLm3qgI",
		"collections": "Emojis|Motivational",
		"downloadable": true,
		"size": 289000,
		"dimensions": "3200 x 4200 px",
		"copyright": "CreativeCommons - CC0"
	},
	
	
					{
		"name": "Glasses",
		"author": "Simplework Designs",
		"url": "https://drive.google.com/uc?export=download&id=1C9IQ9N66sji6DDqGkHhR0tb9iEQRd6C6",
		"thumbnail": "https://drive.google.com/uc?export=download&id=1D9mbV5m5xt63WnLN_Fgy_bKdp81TIdW7",
		"collections": "Emojis",
		"downloadable": true,
		"size": 287000,
		"dimensions": "3200 x 4200 px",
		"copyright": "CreativeCommons - CC0"
	},
	
	
					{
		"name": "Pretty Inside",
		"author": "Simplework Designs",
		"url": "https://drive.google.com/uc?export=download&id=1xH76zEDmUmfKti4bKgZSbt5Zw8wA1us3",
		"thumbnail": "https://drive.google.com/uc?export=download&id=1Jrvl5DhTrXJ1rppKkJ_3D3DsN8MLYnYP",
		"collections": "Rude|Funny",
		"downloadable": true,
		"size": 117000,
		"dimensions": "3200 x 4200 px",
		"copyright": "CreativeCommons - CC0"
	},
	
	
					{
		"name": "Stupid World",
		"author": "Simplework Designs",
		"url": "https://drive.google.com/uc?export=download&id=1BKS_QWrz4l5LsX_YWimQuCatqA2B2OiM",
		"thumbnail": "https://drive.google.com/uc?export=download&id=14WSPOU3YhxrCyLAbEUpG3ylj3SGSf6mu",
		"collections": "Rude|Funny",
		"downloadable": true,
		"size": 213000,
		"dimensions": "3200 x 4200 px",
		"copyright": "CreativeCommons - CC0"
	},
	
	
	
	

	




	
	{
		"name": "Relax",
		"author": "SimpleWork Designs",
		"url": "https://drive.google.com/uc?export=download&id=1QwqaaGilEZyJRzFNBp-N5_zAnuDHBW4Q",
		"thumbnail": "https://drive.google.com/uc?export=download&id=1kqasuaytT4GCYKAnoqzoSMpTT_3gBzo-",
		"collections": "Short Ones",
		"downloadable": true,
		"size": 6110000,
		"dimensions": "3200 x 4200 px",
		"copyright": "CreativeCommons - CC0"
	},
	
			{
		"name": "Rare Breed",
		"author": "SimpleWork Designs",
		"url": "https://drive.google.com/uc?export=download&id=1RGGg_c_IySaBm2ke1BI25HXkvWGdeLbh",
		"thumbnail": "https://drive.google.com/uc?export=download&id=1reJTPn7rwY5HqNiAhOBUj94e3K2Ul3w_",
		"collections": "I am Awesome",
		"downloadable": true,
		"size": 9460000,
		"dimensions": "3200 x 4200 px",
		"copyright": "CreativeCommons - CC0"
	},
	
			{
		"name": "Just Screw It",
		"author": "SimpleWork Designs",
		"url": "https://drive.google.com/uc?export=download&id=1oibgAxi2uhOGKQUOlRG5QqAVfjgcx4BF",
		"thumbnail": "https://drive.google.com/uc?export=download&id=1cwdVvlw99v0sbgXCIOT0TIg2cwSeGgfx",
		"collections": "Motivational|Funny|Brand",
		"downloadable": true,
		"size": 3970000,
		"dimensions": "3200 x 4200 px",
		"copyright": "CreativeCommons - CC0"
	},
	
			{
		"name": "Eating Forever",
		"author": "SimpleWork Designs",
		"url": "https://drive.google.com/uc?export=download&id=1G2gufqVVDWxKIth8JF1_PmQqZy3BvNjK",
		"thumbnail": "https://drive.google.com/uc?export=download&id=1_ki9Ju-7o1aiw3q7goLJotAW2UISyU0d",
		"collections": "I am Awesome",
		"downloadable": true,
		"size": 8740000,
		"dimensions": "3200 x 4200 px",
		"copyright": "CreativeCommons - CC0"
	},
	
			{
		"name": "Common Sense",
		"author": "SimpleWork Designs",
		"url": "https://drive.google.com/uc?export=download&id=142U2K8HY8vv6zUGvdy27grabO3pub5p-",
		"thumbnail": "https://drive.google.com/uc?export=download&id=1VeRU4m3NRBdimcBzPlluPNQZD5dYu_Fk",
		"collections": "Clever",
		"downloadable": true,
		"size": 7690000,
		"dimensions": "3200 x 4200 px",
		"copyright": "CreativeCommons - CC0"
	},
	
			{
		"name": "Excuses",
		"author": "SimpleWork Designs",
		"url": "https://drive.google.com/uc?export=download&id=1N3p4sAM0JTIwbHAIa-T3UkBniJquVkqV",
		"thumbnail": "https://drive.google.com/uc?export=download&id=1-FrzEyGrqFNMs8CNdyohXrfRuNexOIyn",
		"collections": "Motivational",
		"downloadable": true,
		"size": 2740000,
		"dimensions": "3200 x 4200 px",
		"copyright": "CreativeCommons - CC0"
	},
	
			{
		"name": "Iridescent",
		"author": "SimpleWork Designs",
		"url": "https://drive.google.com/uc?export=download&id=15V5yfyCCRdCQL7eOjRN-1TbByhjY3MuT",
		"thumbnail": "https://drive.google.com/uc?export=download&id=12QTRfw4Nmwt6vml3X7chNnX0BwQPuvfN",
		"collections": "Short Ones",
		"downloadable": true,
		"size": 4860000,
		"dimensions": "3200 x 4200 px",
		"copyright": "CreativeCommons - CC0"
	},
	
			{
		"name": "Nefarious",
		"author": "SimpleWork Designs",
		"url": "https://drive.google.com/uc?export=download&id=13A9dtze6T1nLVougAkaS7S57x_oQCF4-",
		"thumbnail": "https://drive.google.com/uc?export=download&id=1KykrkDnX9Ry5Jhsrnd6eKaqJXsN4WiB1",
		"collections": "Short Ones",
		"downloadable": true,
		"size": 9150000,
		"dimensions": "3200 x 4200 px",
		"copyright": "CreativeCommons - CC0"
	},
	
			{
		"name": "Stiffen Up",
		"author": "SimpleWork Designs",
		"url": "https://drive.google.com/uc?export=download&id=1quRPd_fv-pwskQ0RupsCTVs4oOeY1JpW",
		"thumbnail": "https://drive.google.com/uc?export=download&id=1zAsLBhhguuPGQdsOLpaXCpmkpCeATBEt",
		"collections": "Motivational",
		"downloadable": true,
		"size": 9390000,
		"dimensions": "3200 x 4200 px",
		"copyright": "CreativeCommons - CC0"
	},
	
			{
		"name": "Hustle",
		"author": "SimpleWork Designs",
		"url": "https://drive.google.com/uc?export=download&id=1RcoXkO3jdt2XCJKYLzuR6jOHttlsnQjq",
		"thumbnail": "https://drive.google.com/uc?export=download&id=1QcCiOUiyaBeZrEtT4MH-sVB-hIt7FQEY",
		"collections": "Short Ones|Motivational",
		"downloadable": true,
		"size": 4600000,
		"dimensions": "3200 x 4200 px",
		"copyright": "CreativeCommons - CC0"
	},

	
	
	
	
	{
		"name": "Fuc",
		"author": "SimpleWork Designs",
		"url": "https://drive.google.com/uc?export=download&id=1zwmF5XPhr4WputXR5MkcZAAvSYT_06AW",
		"thumbnail": "https://drive.google.com/uc?export=download&id=1HAZkuEfyID1MZaGMkxlg3wI1O7wyzf1I",
		"collections": "Short Ones",
		"downloadable": true,
		"size": 2870000,
		"dimensions": "3200 x 4200 px",
		"copyright": "CreativeCommons - CC0"
	},
	
	
		{
		"name": "Breathe Music",
		"author": "SimpleWork Designs",
		"url": "https://drive.google.com/uc?export=download&id=1KLq4POtGPIfA0-W5HlDkDFWShsubhQBN",
		"thumbnail": "https://drive.google.com/uc?export=download&id=1pzY_khJUKYj6h_LaAfdoDO1Ze72qOYoF",
		"collections": "Short Ones|Quotes",
		"downloadable": true,
		"size": 8160000,
		"dimensions": "3200 x 4200 px",
		"copyright": "CreativeCommons - CC0"
	},
	
	
		{
		"name": "Get it Done",
		"author": "SimpleWork Designs",
		"url": "https://drive.google.com/uc?export=download&id=1lJ8AjJUWZ-RxpOjsTA1HHzVKYz4qYOef",
		"thumbnail": "https://drive.google.com/uc?export=download&id=112KOMiSOVeui2VMRm38BSgRq8SNr-Bpl",
		"collections": "Motivational",
		"downloadable": true,
		"size": 8130000,
		"dimensions": "3200 x 4200 px",
		"copyright": "CreativeCommons - CC0"
	},
	
	
	
	
	
	{
		"name": "Dreamer",
		"author": "SimpleWork Designs",
		"url": "https://drive.google.com/uc?export=download&id=1RGQIIQ439OKk_ZYpbl9BiNmBheKlFgK7",
		"thumbnail": "https://drive.google.com/uc?export=download&id=1e6hsbdvOFGKqCDURrsIEwwA_VbEwDzaw",
		"collections": "Short Ones|Motivational",
		"downloadable": true,
		"size": 8920000,
		"dimensions": "3200 x 4200 px",
		"copyright": "CreativeCommons - CC0"
	},
	
	
	
		{
		"name": "Fuc da Universe",
		"author": "SimpleWork Designs",
		"url": "https://drive.google.com/uc?export=download&id=1kTUM0jJUBsvWk5cP4KPLonpBPavDBmr1",
		"thumbnail": "https://drive.google.com/uc?export=download&id=1Bl3FU8igxQ-tO98Mkwku7sOjDe40RpQK",
		"collections": "Short Ones|Rude",
		"downloadable": true,
		"size": 6830000,
		"dimensions": "3200 x 4200 px",
		"copyright": "CreativeCommons - CC0"
	},
	
	
	
		{
		"name": "Lemons",
		"author": "SimpleWork Designs",
		"url": "https://drive.google.com/uc?export=download&id=1uosqflnBcyHlUQmfJq3ONSRMICM14dk7",
		"thumbnail": "https://drive.google.com/uc?export=download&id=1oel2MtaBsHvaBEeq3LBoVsGb8x_mXjZ5",
		"collections": "Funny|Quotes",
		"downloadable": true,
		"size": 5800000,
		"dimensions": "3200 x 4200 px",
		"copyright": "CreativeCommons - CC0"
	},
	
	
	
		{
		"name": "Best Nightmare",
		"author": "SimpleWork Designs",
		"url": "https://drive.google.com/uc?export=download&id=1LmOISRqN9Jsk3_qZAyJ3W1Nds9ZvmgZ7",
		"thumbnail": "https://drive.google.com/uc?export=download&id=1Vs7_Sk6Su8a5G14Bt2nqrn4uuVTWdWa4",
		"collections": "Funny|Quotes",
		"downloadable": true,
		"size": 5310000,
		"dimensions": "3200 x 4200 px",
		"copyright": "CreativeCommons - CC0"
	},
	
	
	
		{
		"name": "Sarcasm Language",
		"author": "SimpleWork Designs",
		"url": "https://drive.google.com/uc?export=download&id=1Nxgs9D2wRVfkFLSDOeTyuoSkfJ4Orrna",
		"thumbnail": "https://drive.google.com/uc?export=download&id=1cmXeHs02XYdk0caLWevkOOySaiFEL2-T",
		"collections": "Funny",
		"downloadable": true,
		"size": 5010000,
		"dimensions": "3200 x 4200 px",
		"copyright": "CreativeCommons - CC0"
	},
	
	
	
		{
		"name": "Bloody Gorgeous",
		"author": "SimpleWork Designs",
		"url": "https://drive.google.com/uc?export=download&id=1ooWxB26bGUzI2-3gW0CVoJ4pq2jdtwMU",
		"thumbnail": "https://drive.google.com/uc?export=download&id=1Lf9QDi6ewC_hzB1Rn3ysjm2y66gexakn",
		"collections": "I am Awesome",
		"downloadable": true,
		"size": 3730000,
		"dimensions": "3200 x 4200 px",
		"copyright": "CreativeCommons - CC0"
	},
	
	
	
		{
		"name": "Phone not Dic",
		"author": "SimpleWork Designs",
		"url": "https://drive.google.com/uc?export=download&id=1t3C-PZCgRvnkvpIyD9J-owi7wRcSLa73",
		"thumbnail": "https://drive.google.com/uc?export=download&id=1qJdETEZqXwrLItbmtL1P1qGL-UzFYA_r",
		"collections": "Rude|Funny",
		"downloadable": true,
		"size": 9450000,
		"dimensions": "3200 x 4200 px",
		"copyright": "CreativeCommons - CC0"
	},
	
	
	
		{
		"name": "Good Vibes",
		"author": "SimpleWork Designs",
		"url": "https://drive.google.com/uc?export=download&id=1afOOYy2AayIAzbqrrwQQFCL0qy3I_Fim",
		"thumbnail": "https://drive.google.com/uc?export=download&id=12Yijh2SCLCZyXS8eB0_mSHtbdioOQc2K",
		"collections": "Motivational|Short Ones",
		"downloadable": true,
		"size": 3350000,
		"dimensions": "3200 x 4200 px",
		"copyright": "CreativeCommons - CC0"
	},
	
	
	
		{
		"name": "Always Settle",
		"author": "SimpleWork Designs",
		"url": "https://drive.google.com/uc?export=download&id=1aWYTB1S6L5g7ExTzfLpKyd3X03B6QPMd",
		"thumbnail": "https://drive.google.com/uc?export=download&id=1YdamiBYc1BN-sGt-4-MVL_-at1nxoYhE",
		"collections": "Funny|Brand|Short Ones",
		"downloadable": true,
		"size": 9980000,
		"dimensions": "3200 x 4200 px",
		"copyright": "CreativeCommons - CC0"
	},
	
	
	
		{
		"name": "Excerpt for the Stupid",
		"author": "SimpleWork Designs",
		"url": "https://drive.google.com/uc?export=download&id=1G4fX8VImBVjctLgMcon-ro0pc-b_sKzW",
		"thumbnail": "https://drive.google.com/uc?export=download&id=1DkSn0rPEj14_sX_jX6_nXjVeYSmQbv2E",
		"collections": "Funny|Rude",
		"downloadable": true,
		"size": 5250000,
		"dimensions": "3200 x 4200 px",
		"copyright": "CreativeCommons - CC0"
	},
	
	
	
		{
		"name": "Kill Yoself",
		"author": "SimpleWork Designs",
		"url": "https://drive.google.com/uc?export=download&id=1zO6j74bAxjRcLF_M8UX6h7Dyn33L_dkP",
		"thumbnail": "https://drive.google.com/uc?export=download&id=1DdbTwgXKFf0ktuM9TeNd4N519CrX7ZIZ",
		"collections": "Rude|Funny",
		"downloadable": true,
		"size": 4880000,
		"dimensions": "3200 x 4200 px",
		"copyright": "CreativeCommons - CC0"
	},
	
	
	
		{
		"name": "Breathe For Me",
		"author": "SimpleWork Designs",
		"url": "https://drive.google.com/uc?export=download&id=173anEvHQq2ZQYuF9xi2iK3WQhuEEWqhf",
		"thumbnail": "https://drive.google.com/uc?export=download&id=1FaM_gkIIKacNjzQMXh7WFQiY35_3CPFs",
		"collections": "Funny|Quotes",
		"downloadable": true,
		"size": 7280000,
		"dimensions": "3200 x 4200 px",
		"copyright": "CreativeCommons - CC0"
	},
	
	
	
		{
		"name": "Believe in Yoself",
		"author": "SimpleWork Designs",
		"url": "https://drive.google.com/uc?export=download&id=10iGLGc8zYP9V22urxYB6DMQLDB_CUlcn",
		"thumbnail": "https://drive.google.com/uc?export=download&id=1mfyaS2PYeCmvKjRj3lnb77mqEpjuWsSj",
		"collections": "Motivational",
		"downloadable": true,
		"size": 6910000,
		"dimensions": "3200 x 4200 px",
		"copyright": "CreativeCommons - CC0"
	},
	
	
	
		{
		"name": "Mastrubation Face",
		"author": "SimpleWork Designs",
		"url": "https://drive.google.com/uc?export=download&id=1PlgV0gFrrYlSB1VsBlgx7JD7X3PlZC-8",
		"thumbnail": "https://drive.google.com/uc?export=download&id=1EHS2zcvykJG7K6Shhj7fidaUemDaweIH",
		"collections": "Rude|Funny",
		"downloadable": true,
		"size": 8260000,
		"dimensions": "3200 x 4200 px",
		"copyright": "CreativeCommons - CC0"
	},
	
	
	
		{
		"name": "Stup the Game Up",
		"author": "SimpleWork Designs",
		"url": "https://drive.google.com/uc?export=download&id=1NJlJlGpR2CCvXDX2LZOli7NWbt3tn0ZM",
		"thumbnail": "https://drive.google.com/uc?export=download&id=1JEF_c_ncB2roOSKMCkaiufIsSYG7ClnH",
		"collections": "Motivational",
		"downloadable": true,
		"size": 7310000,
		"dimensions": "3200 x 4200 px",
		"copyright": "CreativeCommons - CC0"
	},
	
	
	
		{
		"name": "Run Back to the Zoo",
		"author": "SimpleWork Designs",
		"url": "https://drive.google.com/uc?export=download&id=1dTz919jG9Gnlioy_AfD2THnRvAAnubyD",
		"thumbnail": "https://drive.google.com/uc?export=download&id=1841TGsGLlVuuiG50LsG3NtHnN6dfgfag",
		"collections": "Rude|Funny",
		"downloadable": true,
		"size": 2020000,
		"dimensions": "3200 x 4200 px",
		"copyright": "CreativeCommons - CC0"
	},
	
	
	
		{
		"name": "Not Afraid",
		"author": "SimpleWork Designs",
		"url": "https://drive.google.com/uc?export=download&id=11wR8HDUGE8yUdHUVTECo-S7S9L00gVmI",
		"thumbnail": "https://drive.google.com/uc?export=download&id=19RfP78_DaQ39KDUDvtNeR9WLvb9IKGnB",
		"collections": "Lyrics",
		"downloadable": true,
		"size": 3800000,
		"dimensions": "3200 x 4200 px",
		"copyright": "CreativeCommons - CC0"
	},
	
	
	
		{
		"name": "Thriller",
		"author": "SimpleWork Designs",
		"url": "https://drive.google.com/uc?export=download&id=1a8ei8Te_idk6XE4ptLXNGOkP3f7k5kLg",
		"thumbnail": "https://drive.google.com/uc?export=download&id=1qrJW-kn94Ai8Q4KPsgxMS6yKlKdM2QnH",
		"collections": "Lyrics",
		"downloadable": true,
		"size": 7370000,
		"dimensions": "3200 x 4200 px",
		"copyright": "CreativeCommons - CC0"
	},
	
	
	
		{
		"name": "Shape Of You",
		"author": "SimpleWork Designs",
		"url": "https://drive.google.com/uc?export=download&id=1Sn3wqV-IqrMkxTCbhtN4HM-wxGK8ixb3",
		"thumbnail": "https://drive.google.com/uc?export=download&id=1DzgnF_ItgazIkWur43vIPGhPeBw99U-N",
		"collections": "Lyrics",
		"downloadable": true,
		"size": 8160000,
		"dimensions": "3200 x 4200 px",
		"copyright": "CreativeCommons - CC0"
	},
	
	
	
		{
		"name": "Crazy in Love",
		"author": "SimpleWork Designs",
		"url": "https://drive.google.com/uc?export=download&id=1_jJ7Jp7Jzrhk_QmJFsnZkqDIIrBulNa8",
		"thumbnail": "https://drive.google.com/uc?export=download&id=1Pl-mpzdVCDvIDZTpTT_-DvgrX8K-ezNt",
		"collections": "Lyrics",
		"downloadable": true,
		"size": 6760000,
		"dimensions": "3200 x 4200 px",
		"copyright": "CreativeCommons - CC0"
	},
	
	
	
		{
		"name": "In the End",
		"author": "SimpleWork Designs",
		"url": "https://drive.google.com/uc?export=download&id=1QkN6P9UwoCWcD_LnYbNXYuxqpsXQBIx3",
		"thumbnail": "https://drive.google.com/uc?export=download&id=1qMycQakVmR6rRmWmIIKqFJpeHzDVdQHi",
		"collections": "Lyrics",
		"downloadable": true,
		"size": 6970000,
		"dimensions": "3200 x 4200 px",
		"copyright": "CreativeCommons - CC0"
	},
	
	
	
		{
		"name": "An Offer",
		"author": "SimpleWork Designs",
		"url": "https://drive.google.com/uc?export=download&id=1ke4DGTJXYeZTUgc9Mb-K8zjbYtnsPcI6",
		"thumbnail": "https://drive.google.com/uc?export=download&id=1ZAdBC6-_JMe7DrfK4wL7TihuUJpHHuEr",
		"collections": "Movies",
		"downloadable": true,
		"size": 3720000,
		"dimensions": "3200 x 4200 px",
		"copyright": "CreativeCommons - CC0"
	},
	
	
	
		{
		"name": "Gandalf the Grey",
		"author": "SimpleWork Designs",
		"url": "https://drive.google.com/uc?export=download&id=1S5ZchLzFRNa6y2ItUuHcj1ndNenioeoB",
		"thumbnail": "https://drive.google.com/uc?export=download&id=1U7HLfZZ7f9gBn3nTmWWYJCOz1tgQOFP4",
		"collections": "Movies",
		"downloadable": true,
		"size": 4520000,
		"dimensions": "3200 x 4200 px",
		"copyright": "CreativeCommons - CC0"
	},
	
	
	
		{
		"name": "Fight Club",
		"author": "SimpleWork Designs",
		"url": "https://drive.google.com/uc?export=download&id=1ftsEg_jXn92PcchOKO7exA1y_NOvBXCk",
		"thumbnail": "https://drive.google.com/uc?export=download&id=1EWTFtO4QyVHMPqz6wd4kQetxcctGzoJt",
		"collections": "Movies",
		"downloadable": true,
		"size": 2040000,
		"dimensions": "3200 x 4200 px",
		"copyright": "CreativeCommons - CC0"
	},
	
	
	
		{
		"name": "The Chosen One",
		"author": "SimpleWork Designs",
		"url": "https://drive.google.com/uc?export=download&id=1yQFMxlpkvb-w3cjY6CC2Qed4pGpKftz7",
		"thumbnail": "https://drive.google.com/uc?export=download&id=12sT2OCgQqvSlqIDhWOo-AKSUDdMlOiV8",
		"collections": "Movies",
		"downloadable": true,
		"size": 8780000,
		"dimensions": "3200 x 4200 px",
		"copyright": "CreativeCommons - CC0"
	},
	
	
	
		{
		"name": "Star Wars",
		"author": "SimpleWork Designs",
		"url": "https://drive.google.com/uc?export=download&id=1hU0QmWNQpp2_SpzF0XmhIp31h7Yq7Ewm",
		"thumbnail": "https://drive.google.com/uc?export=download&id=1325TMZieSp4rV_AUtWGoXUj7TZIMc-uK",
		"collections": "Short Ones",
		"downloadable": true,
		"size": 2650000,
		"dimensions": "3200 x 4200 px",
		"copyright": "CreativeCommons - CC0"
	},
	
	
	
		{
		"name": "Shawshank",
		"author": "SimpleWork Designs",
		"url": "https://drive.google.com/uc?export=download&id=16Rm4HmNrhKx4O026bPs0UjW-5NCaABPS",
		"thumbnail": "https://drive.google.com/uc?export=download&id=1d20cBQokIfMltN3jwD4KkptzRTw60z5c",
		"collections": "Movies",
		"downloadable": true,
		"size": 4720000,
		"dimensions": "3200 x 4200 px",
		"copyright": "CreativeCommons - CC0"
	},
	
	
	
		{
		"name": "India",
		"author": "SimpleWork Designs",
		"url": "https://drive.google.com/uc?export=download&id=1nmEdH4RZe1blBkrDjvw-h3fJDUP0CRB2",
		"thumbnail": "https://drive.google.com/uc?export=download&id=1Sx1tz4K9xvRyhK0GgUgQIV1IhjBWItwB",
		"collections": "Countries",
		"downloadable": true,
		"size": 8120000,
		"dimensions": "3200 x 4200 px",
		"copyright": "CreativeCommons - CC0"
	},
	
	
	
		{
		"name": "USA",
		"author": "SimpleWork Designs",
		"url": "https://drive.google.com/uc?export=download&id=1SdsqmFVOJ2uxUOnoHPsUDUBiLN3YWqRP",
		"thumbnail": "https://drive.google.com/uc?export=download&id=1RGCuM2cr-jn1aTr4u0eyf9TgTLgnkGVb",
		"collections": "Countries",
		"downloadable": true,
		"size": 7150000,
		"dimensions": "3200 x 4200 px",
		"copyright": "CreativeCommons - CC0"
	},
	
	
	
		{
		"name": "UK",
		"author": "SimpleWork Designs",
		"url": "https://drive.google.com/uc?export=download&id=1OT7oed3M3RuJtuGoZO2cE0aPBtzsXE7C",
		"thumbnail": "https://drive.google.com/uc?export=download&id=1DtiwWUCLTlgAh0DhWw5DUiSgtzKoy6L-",
		"collections": "Countries",
		"downloadable": true,
		"size": 6010000,
		"dimensions": "3200 x 4200 px",
		"copyright": "CreativeCommons - CC0"
	},
	
	
	
		{
		"name": "Brazil",
		"author": "SimpleWork Designs",
		"url": "https://drive.google.com/uc?export=download&id=1VnvHY76ypA9oAudqVErJ88yGueEbzV6n",
		"thumbnail": "https://drive.google.com/uc?export=download&id=1Ks2nHeYwpMuKeBXnLNrc_uCQSgZQxDLP",
		"collections": "Countries",
		"downloadable": true,
		"size": 3180000,
		"dimensions": "3200 x 4200 px",
		"copyright": "CreativeCommons - CC0"
	},
	
	
	
		{
		"name": "January",
		"author": "SimpleWork Designs",
		"url": "https://drive.google.com/uc?export=download&id=1Oq6m_iuc4pc2jcIeeb0bAu_WRjhDBqAL",
		"thumbnail": "https://drive.google.com/uc?export=download&id=1IQAPGNDM1EtpRUy6YqCzjO40bQiEBvN8",
		"collections": "Month",
		"downloadable": true,
		"size": 405000,
		"dimensions": "3200 x 4200 px",
		"copyright": "CreativeCommons - CC0"
	},
	
	
	
		{
		"name": "February",
		"author": "SimpleWork Designs",
		"url": "https://drive.google.com/uc?export=download&id=1RiMetQiww_K2RTjrW3Q5P3chU0XdoYlf",
		"thumbnail": "https://drive.google.com/uc?export=download&id=162fKusHlwgvMtz5wEm0MJBW-1rVRSFBU",
		"collections": "Month",
		"downloadable": true,
		"size": 253000,
		"dimensions": "3200 x 4200 px",
		"copyright": "CreativeCommons - CC0"
	},
	
	
	
		{
		"name": "March",
		"author": "SimpleWork Designs",
		"url": "https://drive.google.com/uc?export=download&id=1a6lHoCEGuaGIuZcXsf0ts3KE-ZYTb0Kg",
		"thumbnail": "https://drive.google.com/uc?export=download&id=1ih_x9IH64y-TJx1DFkmkf04RlL6Rfnpw",
		"collections": "Month",
		"downloadable": true,
		"size": 391000,
		"dimensions": "3200 x 4200 px",
		"copyright": "CreativeCommons - CC0"
	},
	
	
	
		{
		"name": "April",
		"author": "SimpleWork Designs",
		"url": "https://drive.google.com/uc?export=download&id=17Mz6M9_FohOMOeYQUGfRtfcGD_jvkziy",
		"thumbnail": "https://drive.google.com/uc?export=download&id=1j_pirqARuiLGTSyVInPqipwvUdtQnsRY",
		"collections": "Month",
		"downloadable": true,
		"size": 391000,
		"dimensions": "3200 x 4200 px",
		"copyright": "CreativeCommons - CC0"
	},
	
	
	
		{
		"name": "May",
		"author": "SimpleWork Designs",
		"url": "https://drive.google.com/uc?export=download&id=108kqtV6k7yrl9bkcOdj8lpvTWdA4aRAB",
		"thumbnail": "https://drive.google.com/uc?export=download&id=1B6zJVyBrsJFdWPuiVINMGHqtuk34-NZs",
		"collections": "Month",
		"downloadable": true,
		"size": 344000,
		"dimensions": "3200 x 4200 px",
		"copyright": "CreativeCommons - CC0"
	},
	
	
	
		{
		"name": "June",
		"author": "SimpleWork Designs",
		"url": "https://drive.google.com/uc?export=download&id=1o83GXnuIna1YvJE1xzaUKSuTKjhQXCVe",
		"thumbnail": "https://drive.google.com/uc?export=download&id=1O7_bRJg1v16Y7ZdPbos34W74la0QYyDS",
		"collections": "Month",
		"downloadable": true,
		"size": 351000,
		"dimensions": "3200 x 4200 px",
		"copyright": "CreativeCommons - CC0"
	},
	
	
	
		{
		"name": "July",
		"author": "SimpleWork Designs",
		"url": "https://drive.google.com/uc?export=download&id=1t4EjzJ7cAy8klnnt8VFBilYWJeQkSSZx",
		"thumbnail": "https://drive.google.com/uc?export=download&id=1eAM6SNoZ1J0SpXQazVJAHW1whDWA8yG0",
		"collections": "Month",
		"downloadable": true,
		"size": 333000,
		"dimensions": "3200 x 4200 px",
		"copyright": "CreativeCommons - CC0"
	},
	
	
	
		{
		"name": "August",
		"author": "SimpleWork Designs",
		"url": "https://drive.google.com/uc?export=download&id=1kk7m2JXCUsfJqB9zbiCauPKBuQ6kruDB",
		"thumbnail": "https://drive.google.com/uc?export=download&id=1p7IG9WT7gmI1pDwwjbaWUjQaBJEjLIie",
		"collections": "Month",
		"downloadable": true,
		"size": 241000,
		"dimensions": "3200 x 4200 px",
		"copyright": "CreativeCommons - CC0"
	},
	
	
	
		{
		"name": "September",
		"author": "SimpleWork Designs",
		"url": "https://drive.google.com/uc?export=download&id=1Z2XdjgHcapQhU5cnJp2AAaEZ9AKRUxrS",
		"thumbnail": "https://drive.google.com/uc?export=download&id=1tY4KUwqOhnQMFrhs0oOqtkCPu8FA7iNB",
		"collections": "Month",
		"downloadable": true,
		"size": 245000,
		"dimensions": "3200 x 4200 px",
		"copyright": "CreativeCommons - CC0"
	},
	
	
	
		{
		"name": "October",
		"author": "SimpleWork Designs",
		"url": "https://drive.google.com/uc?export=download&id=1ykrxEVZBtfaElB9frWHQ9Blke7QsgSaf",
		"thumbnail": "https://drive.google.com/uc?export=download&id=1_4Sqs-Dqd-RJhPuABoDgZnAoNbmPv57v",
		"collections": "Month",
		"downloadable": true,
		"size": 339000,
		"dimensions": "3200 x 4200 px",
		"copyright": "CreativeCommons - CC0"
	},
	
	
	
		{
		"name": "November",
		"author": "SimpleWork Designs",
		"url": "https://drive.google.com/uc?export=download&id=15-rqfySiR1kyo-KrTZoin7I9mjEwFiWY",
		"thumbnail": "https://drive.google.com/uc?export=download&id=1X7NQDTz2kA9_aae1gD2mWxVhJT5nw6sS",
		"collections": "Month",
		"downloadable": true,
		"size": 285000,
		"dimensions": "3200 x 4200 px",
		"copyright": "CreativeCommons - CC0"
	},
	
	
	
		{
		"name": "December",
		"author": "SimpleWork Designs",
		"url": "https://drive.google.com/uc?export=download&id=1ZD8gv2EWcmSJOd5T9px2hNRqENiLRDbX",
		"thumbnail": "https://drive.google.com/uc?export=download&id=1O7crKo0rvQF1THHbGJxYhpMCSRzC3t7C",
		"collections": "Month",
		"downloadable": true,
		"size": 272000,
		"dimensions": "3200 x 4200 px",
		"copyright": "CreativeCommons - CC0"
	},
	
	
	
		{
		"name": "One",
		"author": "SimpleWork Designs",
		"url": "https://drive.google.com/uc?export=download&id=1CTeEqbcHqJGzx6JFUvhnmcXaw7IUfshN",
		"thumbnail": "https://drive.google.com/uc?export=download&id=1mpQobqRWvOOqqdKIMAyj5-u0ZIXTqvdH",
		"collections": "Numbers",
		"downloadable": true,
		"size": 4280000,
		"dimensions": "3200 x 4200 px",
		"copyright": "CreativeCommons - CC0"
	},
	
	
	
		{
		"name": "Two",
		"author": "SimpleWork Designs",
		"url": "https://drive.google.com/uc?export=download&id=1rltlaobvIGSZmsbjYMzzGFQwEXFSZSC2",
		"thumbnail": "https://drive.google.com/uc?export=download&id=1nU6Ni52IiPlI2b_6UnZjDyavEc7HZq1J",
		"collections": "Numbers",
		"downloadable": true,
		"size": 4260000,
		"dimensions": "3200 x 4200 px",
		"copyright": "CreativeCommons - CC0"
	},
	
	
	
		{
		"name": "Three",
		"author": "SimpleWork Designs",
		"url": "https://drive.google.com/uc?export=download&id=1TqZD18evD1e0w7GlxKE7nkGGRj2SuN9Y",
		"thumbnail": "https://drive.google.com/uc?export=download&id=1xK9zMrfFPZ3pmJjcXuUZrkbgGsKqUpxj",
		"collections": "Numbers",
		"downloadable": true,
		"size": 4260000,
		"dimensions": "3200 x 4200 px",
		"copyright": "CreativeCommons - CC0"
	},
	
	
	
		{
		"name": "Four",
		"author": "SimpleWork Designs",
		"url": "https://drive.google.com/uc?export=download&id=1qqBhaPmbr9PSLXBpds6U3bbGOGLAyVtM",
		"thumbnail": "https://drive.google.com/uc?export=download&id=1ACfANXB_hYbmTF9pNHcYi64Pi5dyH_Io",
		"collections": "Numbers",
		"downloadable": true,
		"size": 4240000,
		"dimensions": "3200 x 4200 px",
		"copyright": "CreativeCommons - CC0"
	},
	
	
	
		{
		"name": "Five",
		"author": "SimpleWork Designs",
		"url": "https://drive.google.com/uc?export=download&id=1euGU5TEcTqgF6fU4oCO38A99rQh6ptqs",
		"thumbnail": "https://drive.google.com/uc?export=download&id=1_Mw6s4xtnzXa8U4frM4aEeKjSCeTCvM-",
		"collections": "Numbers",
		"downloadable": true,
		"size": 4240000,
		"dimensions": "3200 x 4200 px",
		"copyright": "CreativeCommons - CC0"
	},
	
	
	
		{
		"name": "Six",
		"author": "SimpleWork Designs",
		"url": "https://drive.google.com/uc?export=download&id=1h_Ptanvv5VOTIq8EEjk6E8-dnrwNpGkB",
		"thumbnail": "https://drive.google.com/uc?export=download&id=1wpUg4JfKlS-h_qhqIdG1dWqcRn_012wD",
		"collections": "Numbers",
		"downloadable": true,
		"size": 4260000,
		"dimensions": "3200 x 4200 px",
		"copyright": "CreativeCommons - CC0"
	},
	
	
	
		{
		"name": "Seven",
		"author": "SimpleWork Designs",
		"url": "https://drive.google.com/uc?export=download&id=17fe_E8_h8kwj2todeb9mD14-Eg6mgTEG",
		"thumbnail": "https://drive.google.com/uc?export=download&id=10Qc8qFq0KLdgSKf7DAckmE59aYAAKgkK",
		"collections": "Numbers",
		"downloadable": true,
		"size": 4270000,
		"dimensions": "3200 x 4200 px",
		"copyright": "CreativeCommons - CC0"
	},
	
	
	
		{
		"name": "Eight",
		"author": "SimpleWork Designs",
		"url": "https://drive.google.com/uc?export=download&id=14BbfgxXh9AX9LZmfCaPNo9wDPA4blwYg",
		"thumbnail": "https://drive.google.com/uc?export=download&id=1ZTMuBkdCC-STpFGPyrMgU88JMiY-Gy7f",
		"collections": "Numbers",
		"downloadable": true,
		"size": 4810000,
		"dimensions": "3200 x 4200 px",
		"copyright": "CreativeCommons - CC0"
	},
	
	
	
		{
		"name": "Nine",
		"author": "SimpleWork Designs",
		"url": "https://drive.google.com/uc?export=download&id=1dT4jLWtVxnGl6zUvASm7SBD0Spxjj6-f",
		"thumbnail": "https://drive.google.com/uc?export=download&id=1Cftda_U0pw22nY2TlTQJ-5qB_TFEfKl_",
		"collections": "Numbers",
		"downloadable": true,
		"size": 4260000,
		"dimensions": "3200 x 4200 px",
		"copyright": "CreativeCommons - CC0"
	},
	
	
	
		{
		"name": "Zero",
		"author": "SimpleWork Designs",
		"url": "https://drive.google.com/uc?export=download&id=1A1Nir7KVcNrU0rLA6xrJOAe4HfS6NvhL",
		"thumbnail": "https://drive.google.com/uc?export=download&id=1_AA0C2o2-LCljq_V3QDzb8LVz_aVW8kU",
		"collections": "Numbers",
		"downloadable": true,
		"size": 4250000,
		"dimensions": "3200 x 4200 px",
		"copyright": "CreativeCommons - CC0"
	},
	
	
	
		{
		"name": "A",
		"author": "SimpleWork Designs",
		"url": "https://drive.google.com/uc?export=download&id=18uzb-m8Mi-9_ibxZTAhrGg7PYZUUoRD7",
		"thumbnail": "https://drive.google.com/uc?export=download&id=13xUitRSURs3ozIVuAM4rCqhm6jx9F-ez",
		"collections": "Alphabets",
		"downloadable": true,
		"size": 5810000,
		"dimensions": "3200 x 4200 px",
		"copyright": "CreativeCommons - CC0"
	},
	
	
	
		{
		"name": "B",
		"author": "SimpleWork Designs",
		"url": "https://drive.google.com/uc?export=download&id=14twe7TICooWhk7pVv5cVliWwErXCiL2J",
		"thumbnail": "https://drive.google.com/uc?export=download&id=1KFKODxdMKXGUPu3exaneS3GqU_Knq3nX",
		"collections": "Alphabets",
		"downloadable": true,
		"size": 5790000,
		"dimensions": "3200 x 4200 px",
		"copyright": "CreativeCommons - CC0"
	},
	
	
	
		{
		"name": "C",
		"author": "SimpleWork Designs",
		"url": "https://drive.google.com/uc?export=download&id=1HR23iYzMBzMq0WrS5JuPqVpy1rv_x3Zq",
		"thumbnail": "https://drive.google.com/uc?export=download&id=19mKqmC_Yq2UavqhsJyzUXa1bQwEUGwHy",
		"collections": "Alphabets",
		"downloadable": true,
		"size": 5800000,
		"dimensions": "3200 x 4200 px",
		"copyright": "CreativeCommons - CC0"
	},
	
	
	
		{
		"name": "D",
		"author": "SimpleWork Designs",
		"url": "https://drive.google.com/uc?export=download&id=17CV2UtfBpthMZF_UHhsoDcTLAba_N4IF",
		"thumbnail": "https://drive.google.com/uc?export=download&id=1sCciFyJbB387n2j41ZCAMJpy5uxDLAPQ",
		"collections": "Alphabets",
		"downloadable": true,
		"size": 5790000,
		"dimensions": "3200 x 4200 px",
		"copyright": "CreativeCommons - CC0"
	},
	
	
	
		{
		"name": "E",
		"author": "SimpleWork Designs",
		"url": "https://drive.google.com/uc?export=download&id=1d1HtkUwh0Kz_UP2Ps2G5ZX18athHv0e4",
		"thumbnail": "https://drive.google.com/uc?export=download&id=1i635KqdNHOagb3SbMz3FDvDN-g_612qT",
		"collections": "Alphabets",
		"downloadable": true,
		"size": 5780000,
		"dimensions": "3200 x 4200 px",
		"copyright": "CreativeCommons - CC0"
	},
	
	
	
		{
		"name": "F",
		"author": "SimpleWork Designs",
		"url": "https://drive.google.com/uc?export=download&id=1SogkErh7ocf4tNF6LzoF9mYID0QB3Sid",
		"thumbnail": "https://drive.google.com/uc?export=download&id=1THqY7FwJxeU0FXDRi7NKEX3PpKhm2RE4",
		"collections": "Alphabets",
		"downloadable": true,
		"size": 5800000,
		"dimensions": "3200 x 4200 px",
		"copyright": "CreativeCommons - CC0"
	},
	
	
	
		{
		"name": "G",
		"author": "SimpleWork Designs",
		"url": "https://drive.google.com/uc?export=download&id=1Zj8F9n7zNBtsN298ivy-ns-jHIJ51QQD",
		"thumbnail": "https://drive.google.com/uc?export=download&id=1trSIWfmetM1IsK3pcWMQUYjZkmSL4PRK",
		"collections": "Alphabets",
		"downloadable": true,
		"size": 5790000,
		"dimensions": "3200 x 4200 px",
		"copyright": "CreativeCommons - CC0"
	},
	
	
	
		{
		"name": "H",
		"author": "SimpleWork Designs",
		"url": "https://drive.google.com/uc?export=download&id=1eM3vzppYOnRfh7aUXG3V28YFMyCReHqh",
		"thumbnail": "https://drive.google.com/uc?export=download&id=1fe6QrSCn5jXl31xkvI-SjolEJoZJxw1f",
		"collections": "Alphabets",
		"downloadable": true,
		"size": 5800000,
		"dimensions": "3200 x 4200 px",
		"copyright": "CreativeCommons - CC0"
	},
	
	
	
		{
		"name": "I",
		"author": "SimpleWork Designs",
		"url": "https://drive.google.com/uc?export=download&id=10ynYUDn6B8nzKj7FaLwTklW0e4JKCiXx",
		"thumbnail": "https://drive.google.com/uc?export=download&id=1fki491eCPbf0FfZzwJ2PHFl-4GADmsSf",
		"collections": "Alphabets",
		"downloadable": true,
		"size": 5800000,
		"dimensions": "3200 x 4200 px",
		"copyright": "CreativeCommons - CC0"
	},
	
	
	
		{
		"name": "J",
		"author": "SimpleWork Designs",
		"url": "https://drive.google.com/uc?export=download&id=15PLau572pWMRhstEqfqX3DMFZkbX9qiY",
		"thumbnail": "https://drive.google.com/uc?export=download&id=1iZ_Rmu27UD948yGMjIxvsXfaAtEQ6XM9",
		"collections": "Alphabets",
		"downloadable": true,
		"size": 5800000,
		"dimensions": "3200 x 4200 px",
		"copyright": "CreativeCommons - CC0"
	},
	
	
	
		{
		"name": "K",
		"author": "SimpleWork Designs",
		"url": "https://drive.google.com/uc?export=download&id=1ViA4K3jU-BvlVrulnazRDsd3Q7xxC-1c",
		"thumbnail": "https://drive.google.com/uc?export=download&id=1EycwyHyr9CmOCWt0oc_3pjNzWiOBWcEG",
		"collections": "Alphabets",
		"downloadable": true,
		"size": 5790000,
		"dimensions": "3200 x 4200 px",
		"copyright": "CreativeCommons - CC0"
	},
	
	
	
		{
		"name": "L",
		"author": "SimpleWork Designs",
		"url": "https://drive.google.com/uc?export=download&id=1k5wBtfsaMozfZo8IX-hmoDIVPiCYQ_5t",
		"thumbnail": "https://drive.google.com/uc?export=download&id=1wOZApi1YuKGNUJZM_OOpfMnYpcsjmrKj",
		"collections": "Alphabets",
		"downloadable": true,
		"size": 5790000,
		"dimensions": "3200 x 4200 px",
		"copyright": "CreativeCommons - CC0"
	},
	
	
	
		{
		"name": "M",
		"author": "SimpleWork Designs",
		"url": "https://drive.google.com/uc?export=download&id=1Ixd-k6C1h_JDW6Ft8sbHd9brLFX7Pi5h",
		"thumbnail": "https://drive.google.com/uc?export=download&id=1bX1DM68PKPO4b8O-Ah2Iv1uT-FsgpBKQ",
		"collections": "Alphabets",
		"downloadable": true,
		"size": 5780000,
		"dimensions": "3200 x 4200 px",
		"copyright": "CreativeCommons - CC0"
	},
	
	
	
		{
		"name": "N",
		"author": "SimpleWork Designs",
		"url": "https://drive.google.com/uc?export=download&id=1ge3SxrD0DZhblimEqTxYljwKdLGvjvjN",
		"thumbnail": "https://drive.google.com/uc?export=download&id=1XO_8KZR4SMFdbFEQ_hB5LFSJnOtiJXak",
		"collections": "Alphabets",
		"downloadable": true,
		"size": 5770000,
		"dimensions": "3200 x 4200 px",
		"copyright": "CreativeCommons - CC0"
	},
	
	
	
	
			{
		"name": "O",
		"author": "SimpleWork Designs",
		"url": "https://drive.google.com/uc?export=download&id=1XVRO-Jqxg1ZeY4qpYzj2aXului20DfkT",
		"thumbnail": "https://drive.google.com/uc?export=download&id=1t_9b0MqSnW8NwPkH7fkR1PRmY976PwO7",
		"collections": "Alphabets",
		"downloadable": true,
		"size": 5800000,
		"dimensions": "3200 x 4200 px",
		"copyright": "CreativeCommons - CC0"
	},
	
	
			{
		"name": "P",
		"author": "SimpleWork Designs",
		"url": "https://drive.google.com/uc?export=download&id=1ooA0rYtkOlKzt6zLXxguIsFv7Z5XSREY",
		"thumbnail": "https://drive.google.com/uc?export=download&id=1YCncDAgTySHaB83t986GpOWDFEy6BAUL",
		"collections": "Alphabets",
		"downloadable": true,
		"size": 5790000,
		"dimensions": "3200 x 4200 px",
		"copyright": "CreativeCommons - CC0"
	},
			{
		"name": "Q",
		"author": "SimpleWork Designs",
		"url": "https://drive.google.com/uc?export=download&id=1v6dywuurd8vB1lrjv2NlhCZEFvwZinmI",
		"thumbnail": "https://drive.google.com/uc?export=download&id=1TCh-acO8u5-p97NYx_rh0j5VtZlHJXqt",
		"collections": "Alphabets",
		"downloadable": true,
		"size": 5790000,
		"dimensions": "3200 x 4200 px",
		"copyright": "CreativeCommons - CC0"
	},
			{
		"name": "R",
		"author": "SimpleWork Designs",
		"url": "https://drive.google.com/uc?export=download&id=1QLLqF3G7tqmvNRhexiA_ShG14Iqgq9NL",
		"thumbnail": "https://drive.google.com/uc?export=download&id=17bEiWBcq_GdQTFQRqqH70LW_NP6koFPo",
		"collections": "Alphabets",
		"downloadable": true,
		"size": 5790000,
		"dimensions": "3200 x 4200 px",
		"copyright": "CreativeCommons - CC0"
	},
			{
		"name": "S",
		"author": "SimpleWork Designs",
		"url": "https://drive.google.com/uc?export=download&id=1FwDSmD8SLueP62Fml35K7LBa7v4bvrgf",
		"thumbnail": "https://drive.google.com/uc?export=download&id=1_Jf7DCbx2j_anyawu-x6WKSex8tO669-",
		"collections": "Alphabets",
		"downloadable": true,
		"size": 5800000,
		"dimensions": "3200 x 4200 px",
		"copyright": "CreativeCommons - CC0"
	},
			{
		"name": "T",
		"author": "SimpleWork Designs",
		"url": "https://drive.google.com/uc?export=download&id=1gaEf1DRosFjccRMvRPrn8Wk4_vyzB7Lp",
		"thumbnail": "https://drive.google.com/uc?export=download&id=1IC5nT0BtR4-WHVtKmCvUp9RPLQtCqwby",
		"collections": "Alphabets",
		"downloadable": true,
		"size": 5800000,
		"dimensions": "3200 x 4200 px",
		"copyright": "CreativeCommons - CC0"
	},
			{
		"name": "U",
		"author": "SimpleWork Designs",
		"url": "https://drive.google.com/uc?export=download&id=1kb73-58yaf7hNZmYfAzghdyovWqJBlY5",
		"thumbnail": "https://drive.google.com/uc?export=download&id=1eBXB9SX8ncD_XGZflxvKlnn23kP1Qx7V",
		"collections": "Alphabets",
		"downloadable": true,
		"size": 5790000,
		"dimensions": "3200 x 4200 px",
		"copyright": "CreativeCommons - CC0"
	},
			{
		"name": "V",
		"author": "SimpleWork Designs",
		"url": "https://drive.google.com/uc?export=download&id=166hS9k71E-1M_CyBQfFO5j5_nqoKurQI",
		"thumbnail": "https://drive.google.com/uc?export=download&id=1tKExc0APg8EKAuaZvnvNJOJuS9yvnq4r",
		"collections": "Alphabets",
		"downloadable": true,
		"size": 5800000,
		"dimensions": "3200 x 4200 px",
		"copyright": "CreativeCommons - CC0"
	},
			{
		"name": "W",
		"author": "SimpleWork Designs",
		"url": "https://drive.google.com/uc?export=download&id=1PPvJcHBqPvXxh1HrSshgTMinYrr4dViG",
		"thumbnail": "https://drive.google.com/uc?export=download&id=1Zf-WJVf7cnzId9PKqFV2zBxCyy-k3enI",
		"collections": "Alphabets",
		"downloadable": true,
		"size": 5790000,
		"dimensions": "3200 x 4200 px",
		"copyright": "CreativeCommons - CC0"
	},
			{
		"name": "X",
		"author": "SimpleWork Designs",
		"url": "https://drive.google.com/uc?export=download&id=1-bF-FUY7Y4Y6_PXYwcZEBf-w_lrT740r",
		"thumbnail": "https://drive.google.com/uc?export=download&id=1vc5FXiQsnt8iZGwcQpuO5imnee-ReoPK",
		"collections": "Alphabets",
		"downloadable": true,
		"size": 5800000,
		"dimensions": "3200 x 4200 px",
		"copyright": "CreativeCommons - CC0"
	},
			{
		"name": "Y",
		"author": "SimpleWork Designs",
		"url": "https://drive.google.com/uc?export=download&id=1G7wRg2CR13B2Kvue3CQhJ3Is-ftB-H1D",
		"thumbnail": "https://drive.google.com/uc?export=download&id=1Dj5xaD0NGR6Dg2JN2gmjxDE11AqF2TZr",
		"collections": "Alphabets",
		"downloadable": true,
		"size": 5810000,
		"dimensions": "3200 x 4200 px",
		"copyright": "CreativeCommons - CC0"
	},
			{
		"name": "Z",
		"author": "SimpleWork Designs",
		"url": "https://drive.google.com/uc?export=download&id=1S0T-D24KDCrCrEnm-KlW8BFrwXMOOMYJ",
		"thumbnail": "https://drive.google.com/uc?export=download&id=1IF86igHViyYfpyhQRMsniUjt0rVmm4D8",
		"collections": "Alphabets",
		"downloadable": true,
		"size": 5790000,
		"dimensions": "3200 x 4200 px",
		"copyright": "CreativeCommons - CC0"
	}
	
	
	
	

]
